{"responses": [{"textAnnotations": [{"locale": "und", "description": "STERN Viktor Israel\n106203\nJulius u. Mathilde Elisabeth Wilhelmin RUDOLPH\n17.6.43\nResi Markhoff\n18.12.1914 Berlin\ni. Berlin verhaftet\nis.\ndeutsch\n29.6.1943 n. Theresienstadt überst.i/97-13500 (Transp)\n30.9.1944 i. KL Golleschau (Kom. Auschwitz) H.Nr. B-11329\n6.2.1945 i. KL Flossenbürg H.Nr.47004\n16.3.1945 i. KL Leonberg (Kom Natzweiler)\n28.3.45\n2.5.45\ni. KL Dachau H.Nr. 146772\ni. Dachau befreit.\nHenry Marc Stern, Germering\n21.11.90\n35\n14.5.91Wil.", "boundingPoly": {"vertices": [{"x": 8, "y": 42}, {"x": 1129, "y": 42}, {"x": 1129, "y": 714}, {"x": 8, "y": 714}]}}, {"description": "STERN", "boundingPoly": {"vertices": [{"x": 259, "y": 42}, {"x": 428, "y": 44}, {"x": 428, "y": 75}, {"x": 259, "y": 73}]}}, {"description": "Viktor", "boundingPoly": {"vertices": [{"x": 463, "y": 44}, {"x": 579, "y": 45}, {"x": 579, "y": 76}, {"x": 463, "y": 75}]}}, {"description": "Israel", "boundingPoly": {"vertices": [{"x": 599, "y": 46}, {"x": 710, "y": 47}, {"x": 710, "y": 78}, {"x": 599, "y": 77}]}}, {"description": "106203", "boundingPoly": {"vertices": [{"x": 845, "y": 58}, {"x": 1086, "y": 57}, {"x": 1086, "y": 113}, {"x": 845, "y": 114}]}}, {"description": "Julius", "boundingPoly": {"vertices": [{"x": 261, "y": 126}, {"x": 372, "y": 127}, {"x": 372, "y": 157}, {"x": 261, "y": 156}]}}, {"description": "u", "boundingPoly": {"vertices": [{"x": 392, "y": 128}, {"x": 408, "y": 128}, {"x": 408, "y": 157}, {"x": 392, "y": 157}]}}, {"description": ".", "boundingPoly": {"vertices": [{"x": 414, "y": 128}, {"x": 423, "y": 128}, {"x": 423, "y": 157}, {"x": 414, "y": 157}]}}, {"description": "Mathilde", "boundingPoly": {"vertices": [{"x": 447, "y": 128}, {"x": 598, "y": 130}, {"x": 598, "y": 160}, {"x": 447, "y": 158}]}}, {"description": "Elisabeth", "boundingPoly": {"vertices": [{"x": 617, "y": 130}, {"x": 785, "y": 132}, {"x": 785, "y": 162}, {"x": 617, "y": 160}]}}, {"description": "Wilhelmin", "boundingPoly": {"vertices": [{"x": 805, "y": 132}, {"x": 974, "y": 134}, {"x": 974, "y": 164}, {"x": 805, "y": 162}]}}, {"description": "RUDOLPH", "boundingPoly": {"vertices": [{"x": 997, "y": 134}, {"x": 1127, "y": 135}, {"x": 1127, "y": 165}, {"x": 997, "y": 164}]}}, {"description": "17.6.43", "boundingPoly": {"vertices": [{"x": 12, "y": 354}, {"x": 144, "y": 355}, {"x": 144, "y": 381}, {"x": 12, "y": 380}]}}, {"description": "Resi", "boundingPoly": {"vertices": [{"x": 258, "y": 243}, {"x": 334, "y": 244}, {"x": 334, "y": 270}, {"x": 258, "y": 269}]}}, {"description": "Markhoff", "boundingPoly": {"vertices": [{"x": 353, "y": 243}, {"x": 502, "y": 244}, {"x": 502, "y": 271}, {"x": 353, "y": 270}]}}, {"description": "18.12.1914", "boundingPoly": {"vertices": [{"x": 259, "y": 317}, {"x": 445, "y": 319}, {"x": 445, "y": 347}, {"x": 259, "y": 345}]}}, {"description": "Berlin", "boundingPoly": {"vertices": [{"x": 464, "y": 319}, {"x": 578, "y": 320}, {"x": 578, "y": 348}, {"x": 464, "y": 347}]}}, {"description": "i", "boundingPoly": {"vertices": [{"x": 257, "y": 356}, {"x": 276, "y": 356}, {"x": 276, "y": 382}, {"x": 257, "y": 382}]}}, {"description": ".", "boundingPoly": {"vertices": [{"x": 282, "y": 356}, {"x": 293, "y": 356}, {"x": 293, "y": 382}, {"x": 282, "y": 382}]}}, {"description": "Berlin", "boundingPoly": {"vertices": [{"x": 316, "y": 356}, {"x": 426, "y": 357}, {"x": 426, "y": 383}, {"x": 316, "y": 382}]}}, {"description": "verhaftet", "boundingPoly": {"vertices": [{"x": 447, "y": 357}, {"x": 614, "y": 359}, {"x": 614, "y": 386}, {"x": 447, "y": 384}]}}, {"description": "is", "boundingPoly": {"vertices": [{"x": 900, "y": 252}, {"x": 935, "y": 253}, {"x": 934, "y": 278}, {"x": 899, "y": 277}]}}, {"description": ".", "boundingPoly": {"vertices": [{"x": 943, "y": 252}, {"x": 952, "y": 252}, {"x": 951, "y": 277}, {"x": 942, "y": 277}]}}, {"description": "deutsch", "boundingPoly": {"vertices": [{"x": 900, "y": 289}, {"x": 1031, "y": 291}, {"x": 1031, "y": 316}, {"x": 900, "y": 314}]}}, {"description": "29.6.1943", "boundingPoly": {"vertices": [{"x": 11, "y": 392}, {"x": 181, "y": 393}, {"x": 181, "y": 420}, {"x": 11, "y": 419}]}}, {"description": "n", "boundingPoly": {"vertices": [{"x": 260, "y": 393}, {"x": 277, "y": 393}, {"x": 277, "y": 423}, {"x": 260, "y": 423}]}}, {"description": ".", "boundingPoly": {"vertices": [{"x": 283, "y": 393}, {"x": 292, "y": 393}, {"x": 292, "y": 423}, {"x": 283, "y": 423}]}}, {"description": "Theresienstadt", "boundingPoly": {"vertices": [{"x": 314, "y": 393}, {"x": 577, "y": 397}, {"x": 577, "y": 428}, {"x": 314, "y": 424}]}}, {"description": "überst.i", "boundingPoly": {"vertices": [{"x": 597, "y": 397}, {"x": 748, "y": 399}, {"x": 748, "y": 430}, {"x": 597, "y": 428}]}}, {"description": "/", "boundingPoly": {"vertices": [{"x": 750, "y": 400}, {"x": 765, "y": 400}, {"x": 765, "y": 430}, {"x": 750, "y": 430}]}}, {"description": "97-13500", "boundingPoly": {"vertices": [{"x": 767, "y": 399}, {"x": 916, "y": 401}, {"x": 916, "y": 432}, {"x": 767, "y": 430}]}}, {"description": "(", "boundingPoly": {"vertices": [{"x": 924, "y": 402}, {"x": 935, "y": 402}, {"x": 935, "y": 432}, {"x": 924, "y": 432}]}}, {"description": "Transp", "boundingPoly": {"vertices": [{"x": 937, "y": 402}, {"x": 1050, "y": 404}, {"x": 1050, "y": 435}, {"x": 937, "y": 433}]}}, {"description": ")", "boundingPoly": {"vertices": [{"x": 1052, "y": 404}, {"x": 1065, "y": 404}, {"x": 1065, "y": 434}, {"x": 1052, "y": 434}]}}, {"description": "30.9.1944", "boundingPoly": {"vertices": [{"x": 11, "y": 430}, {"x": 181, "y": 431}, {"x": 181, "y": 457}, {"x": 11, "y": 456}]}}, {"description": "i", "boundingPoly": {"vertices": [{"x": 258, "y": 431}, {"x": 276, "y": 431}, {"x": 276, "y": 460}, {"x": 258, "y": 460}]}}, {"description": ".", "boundingPoly": {"vertices": [{"x": 282, "y": 431}, {"x": 291, "y": 431}, {"x": 291, "y": 460}, {"x": 282, "y": 460}]}}, {"description": "KL", "boundingPoly": {"vertices": [{"x": 314, "y": 431}, {"x": 353, "y": 432}, {"x": 353, "y": 462}, {"x": 314, "y": 461}]}}, {"description": "Golleschau", "boundingPoly": {"vertices": [{"x": 372, "y": 432}, {"x": 558, "y": 434}, {"x": 558, "y": 463}, {"x": 372, "y": 461}]}}, {"description": "(", "boundingPoly": {"vertices": [{"x": 565, "y": 435}, {"x": 574, "y": 435}, {"x": 574, "y": 464}, {"x": 565, "y": 464}]}}, {"description": "Kom", "boundingPoly": {"vertices": [{"x": 577, "y": 434}, {"x": 633, "y": 435}, {"x": 633, "y": 465}, {"x": 577, "y": 464}]}}, {"description": ".", "boundingPoly": {"vertices": [{"x": 640, "y": 435}, {"x": 649, "y": 435}, {"x": 649, "y": 464}, {"x": 640, "y": 464}]}}, {"description": "Auschwitz", "boundingPoly": {"vertices": [{"x": 651, "y": 435}, {"x": 821, "y": 437}, {"x": 821, "y": 467}, {"x": 651, "y": 465}]}}, {"description": ")", "boundingPoly": {"vertices": [{"x": 827, "y": 438}, {"x": 836, "y": 438}, {"x": 836, "y": 467}, {"x": 827, "y": 467}]}}, {"description": "H.Nr.", "boundingPoly": {"vertices": [{"x": 843, "y": 438}, {"x": 932, "y": 439}, {"x": 932, "y": 469}, {"x": 843, "y": 468}]}}, {"description": "B", "boundingPoly": {"vertices": [{"x": 937, "y": 439}, {"x": 955, "y": 439}, {"x": 955, "y": 468}, {"x": 937, "y": 468}]}}, {"description": "-", "boundingPoly": {"vertices": [{"x": 957, "y": 440}, {"x": 973, "y": 440}, {"x": 973, "y": 469}, {"x": 957, "y": 469}]}}, {"description": "11329", "boundingPoly": {"vertices": [{"x": 975, "y": 440}, {"x": 1067, "y": 441}, {"x": 1067, "y": 470}, {"x": 975, "y": 469}]}}, {"description": "6.2.1945", "boundingPoly": {"vertices": [{"x": 11, "y": 469}, {"x": 160, "y": 468}, {"x": 160, "y": 494}, {"x": 11, "y": 495}]}}, {"description": "i", "boundingPoly": {"vertices": [{"x": 258, "y": 471}, {"x": 277, "y": 471}, {"x": 277, "y": 504}, {"x": 258, "y": 504}]}}, {"description": ".", "boundingPoly": {"vertices": [{"x": 281, "y": 471}, {"x": 291, "y": 471}, {"x": 291, "y": 504}, {"x": 281, "y": 504}]}}, {"description": "KL", "boundingPoly": {"vertices": [{"x": 315, "y": 471}, {"x": 354, "y": 471}, {"x": 354, "y": 504}, {"x": 315, "y": 504}]}}, {"description": "Flossenbürg", "boundingPoly": {"vertices": [{"x": 370, "y": 471}, {"x": 578, "y": 472}, {"x": 578, "y": 506}, {"x": 370, "y": 505}]}}, {"description": "H.Nr.47004", "boundingPoly": {"vertices": [{"x": 597, "y": 472}, {"x": 786, "y": 473}, {"x": 786, "y": 507}, {"x": 597, "y": 506}]}}, {"description": "16.3.1945", "boundingPoly": {"vertices": [{"x": 12, "y": 508}, {"x": 181, "y": 508}, {"x": 181, "y": 533}, {"x": 12, "y": 533}]}}, {"description": "i", "boundingPoly": {"vertices": [{"x": 258, "y": 508}, {"x": 276, "y": 508}, {"x": 276, "y": 539}, {"x": 258, "y": 539}]}}, {"description": ".", "boundingPoly": {"vertices": [{"x": 282, "y": 508}, {"x": 292, "y": 508}, {"x": 292, "y": 539}, {"x": 282, "y": 539}]}}, {"description": "KL", "boundingPoly": {"vertices": [{"x": 315, "y": 508}, {"x": 352, "y": 508}, {"x": 352, "y": 539}, {"x": 315, "y": 539}]}}, {"description": "Leonberg", "boundingPoly": {"vertices": [{"x": 371, "y": 508}, {"x": 519, "y": 509}, {"x": 519, "y": 541}, {"x": 371, "y": 540}]}}, {"description": "(", "boundingPoly": {"vertices": [{"x": 527, "y": 510}, {"x": 537, "y": 510}, {"x": 537, "y": 541}, {"x": 527, "y": 541}]}}, {"description": "Kom", "boundingPoly": {"vertices": [{"x": 541, "y": 510}, {"x": 597, "y": 510}, {"x": 597, "y": 541}, {"x": 541, "y": 541}]}}, {"description": "Natzweiler", "boundingPoly": {"vertices": [{"x": 615, "y": 510}, {"x": 803, "y": 512}, {"x": 803, "y": 544}, {"x": 615, "y": 542}]}}, {"description": ")", "boundingPoly": {"vertices": [{"x": 806, "y": 512}, {"x": 818, "y": 512}, {"x": 818, "y": 543}, {"x": 806, "y": 543}]}}, {"description": "28.3.45", "boundingPoly": {"vertices": [{"x": 9, "y": 546}, {"x": 141, "y": 546}, {"x": 141, "y": 571}, {"x": 9, "y": 571}]}}, {"description": "2.5.45", "boundingPoly": {"vertices": [{"x": 9, "y": 581}, {"x": 122, "y": 583}, {"x": 121, "y": 611}, {"x": 8, "y": 609}]}}, {"description": "i", "boundingPoly": {"vertices": [{"x": 258, "y": 547}, {"x": 275, "y": 547}, {"x": 275, "y": 576}, {"x": 258, "y": 576}]}}, {"description": ".", "boundingPoly": {"vertices": [{"x": 281, "y": 547}, {"x": 290, "y": 547}, {"x": 290, "y": 576}, {"x": 281, "y": 576}]}}, {"description": "KL", "boundingPoly": {"vertices": [{"x": 313, "y": 547}, {"x": 352, "y": 547}, {"x": 352, "y": 576}, {"x": 313, "y": 576}]}}, {"description": "Dachau", "boundingPoly": {"vertices": [{"x": 371, "y": 547}, {"x": 481, "y": 548}, {"x": 481, "y": 578}, {"x": 371, "y": 577}]}}, {"description": "H.Nr.", "boundingPoly": {"vertices": [{"x": 504, "y": 548}, {"x": 590, "y": 549}, {"x": 590, "y": 579}, {"x": 504, "y": 578}]}}, {"description": "146772", "boundingPoly": {"vertices": [{"x": 616, "y": 549}, {"x": 726, "y": 550}, {"x": 726, "y": 579}, {"x": 616, "y": 578}]}}, {"description": "i", "boundingPoly": {"vertices": [{"x": 256, "y": 585}, {"x": 274, "y": 585}, {"x": 274, "y": 611}, {"x": 256, "y": 611}]}}, {"description": ".", "boundingPoly": {"vertices": [{"x": 280, "y": 585}, {"x": 291, "y": 585}, {"x": 291, "y": 611}, {"x": 280, "y": 611}]}}, {"description": "Dachau", "boundingPoly": {"vertices": [{"x": 313, "y": 585}, {"x": 426, "y": 586}, {"x": 426, "y": 613}, {"x": 313, "y": 612}]}}, {"description": "befreit", "boundingPoly": {"vertices": [{"x": 446, "y": 587}, {"x": 577, "y": 589}, {"x": 577, "y": 615}, {"x": 446, "y": 613}]}}, {"description": ".", "boundingPoly": {"vertices": [{"x": 582, "y": 589}, {"x": 593, "y": 589}, {"x": 593, "y": 615}, {"x": 582, "y": 615}]}}, {"description": "Henry", "boundingPoly": {"vertices": [{"x": 9, "y": 640}, {"x": 105, "y": 641}, {"x": 105, "y": 672}, {"x": 9, "y": 671}]}}, {"description": "Marc", "boundingPoly": {"vertices": [{"x": 123, "y": 640}, {"x": 198, "y": 640}, {"x": 198, "y": 672}, {"x": 123, "y": 672}]}}, {"description": "Stern", "boundingPoly": {"vertices": [{"x": 218, "y": 641}, {"x": 311, "y": 642}, {"x": 311, "y": 673}, {"x": 218, "y": 672}]}}, {"description": ",", "boundingPoly": {"vertices": [{"x": 319, "y": 641}, {"x": 327, "y": 641}, {"x": 327, "y": 672}, {"x": 319, "y": 672}]}}, {"description": "Germering", "boundingPoly": {"vertices": [{"x": 351, "y": 641}, {"x": 520, "y": 642}, {"x": 520, "y": 674}, {"x": 351, "y": 673}]}}, {"description": "21.11.90", "boundingPoly": {"vertices": [{"x": 8, "y": 678}, {"x": 161, "y": 679}, {"x": 161, "y": 704}, {"x": 8, "y": 703}]}}, {"description": "35", "boundingPoly": {"vertices": [{"x": 1068, "y": 633}, {"x": 1129, "y": 634}, {"x": 1128, "y": 680}, {"x": 1067, "y": 679}]}}, {"description": "14.5.91Wil", "boundingPoly": {"vertices": [{"x": 898, "y": 685}, {"x": 1085, "y": 688}, {"x": 1085, "y": 714}, {"x": 898, "y": 711}]}}, {"description": ".", "boundingPoly": {"vertices": [{"x": 1089, "y": 688}, {"x": 1099, "y": 688}, {"x": 1099, "y": 713}, {"x": 1089, "y": 713}]}}], "fullTextAnnotation": {"pages": [{"property": {"detectedLanguages": [{"languageCode": "de", "confidence": 0.1648746}, {"languageCode": "en", "confidence": 0.14499271}, {"languageCode": "sv", "confidence": 0.043572243}]}, "width": 1142, "height": 739, "blocks": [{"boundingBox": {"vertices": [{"x": 259, "y": 42}, {"x": 710, "y": 47}, {"x": 710, "y": 78}, {"x": 259, "y": 73}]}, "paragraphs": [{"boundingBox": {"vertices": [{"x": 259, "y": 42}, {"x": 710, "y": 47}, {"x": 710, "y": 78}, {"x": 259, "y": 73}]}, "words": [{"property": {"detectedLanguages": [{"languageCode": "sv", "confidence": 1}]}, "boundingBox": {"vertices": [{"x": 259, "y": 42}, {"x": 428, "y": 44}, {"x": 428, "y": 75}, {"x": 259, "y": 73}]}, "symbols": [{"boundingBox": {"vertices": [{"x": 259, "y": 43}, {"x": 279, "y": 43}, {"x": 279, "y": 73}, {"x": 259, "y": 73}]}, "text": "S"}, {"boundingBox": {"vertices": [{"x": 296, "y": 43}, {"x": 318, "y": 43}, {"x": 318, "y": 73}, {"x": 296, "y": 73}]}, "text": "T"}, {"boundingBox": {"vertices": [{"x": 334, "y": 43}, {"x": 352, "y": 43}, {"x": 352, "y": 73}, {"x": 334, "y": 73}]}, "text": "E"}, {"boundingBox": {"vertices": [{"x": 371, "y": 44}, {"x": 392, "y": 44}, {"x": 392, "y": 74}, {"x": 371, "y": 74}]}, "text": "R"}, {"property": {"detectedBreak": {"type": "SPACE"}}, "boundingBox": {"vertices": [{"x": 408, "y": 44}, {"x": 428, "y": 44}, {"x": 428, "y": 74}, {"x": 408, "y": 74}]}, "text": "N"}]}, {"property": {"detectedLanguages": [{"languageCode": "sv", "confidence": 1}]}, "boundingBox": {"vertices": [{"x": 463, "y": 44}, {"x": 579, "y": 45}, {"x": 579, "y": 76}, {"x": 463, "y": 75}]}, "symbols": [{"boundingBox": {"vertices": [{"x": 463, "y": 45}, {"x": 486, "y": 45}, {"x": 486, "y": 75}, {"x": 463, "y": 75}]}, "text": "V"}, {"boundingBox": {"vertices": [{"x": 486, "y": 45}, {"x": 502, "y": 45}, {"x": 502, "y": 75}, {"x": 486, "y": 75}]}, "text": "i"}, {"boundingBox": {"vertices": [{"x": 503, "y": 45}, {"x": 520, "y": 45}, {"x": 520, "y": 75}, {"x": 503, "y": 75}]}, "text": "k"}, {"boundingBox": {"vertices": [{"x": 521, "y": 45}, {"x": 538, "y": 45}, {"x": 538, "y": 75}, {"x": 521, "y": 75}]}, "text": "t"}, {"boundingBox": {"vertices": [{"x": 541, "y": 46}, {"x": 558, "y": 46}, {"x": 558, "y": 76}, {"x": 541, "y": 76}]}, "text": "o"}, {"property": {"detectedBreak": {"type": "SPACE"}}, "boundingBox": {"vertices": [{"x": 559, "y": 46}, {"x": 579, "y": 46}, {"x": 579, "y": 76}, {"x": 559, "y": 76}]}, "text": "r"}]}, {"property": {"detectedLanguages": [{"languageCode": "sv", "confidence": 1}]}, "boundingBox": {"vertices": [{"x": 599, "y": 46}, {"x": 710, "y": 47}, {"x": 710, "y": 78}, {"x": 599, "y": 77}]}, "symbols": [{"boundingBox": {"vertices": [{"x": 599, "y": 46}, {"x": 614, "y": 46}, {"x": 614, "y": 76}, {"x": 599, "y": 76}]}, "text": "I"}, {"boundingBox": {"vertices": [{"x": 617, "y": 46}, {"x": 634, "y": 46}, {"x": 634, "y": 76}, {"x": 617, "y": 76}]}, "text": "s"}, {"boundingBox": {"vertices": [{"x": 635, "y": 47}, {"x": 651, "y": 47}, {"x": 651, "y": 77}, {"x": 635, "y": 77}]}, "text": "r"}, {"boundingBox": {"vertices": [{"x": 655, "y": 47}, {"x": 670, "y": 47}, {"x": 670, "y": 77}, {"x": 655, "y": 77}]}, "text": "a"}, {"boundingBox": {"vertices": [{"x": 673, "y": 47}, {"x": 689, "y": 47}, {"x": 689, "y": 77}, {"x": 673, "y": 77}]}, "text": "e"}, {"property": {"detectedBreak": {"type": "LINE_BREAK"}}, "boundingBox": {"vertices": [{"x": 694, "y": 47}, {"x": 710, "y": 47}, {"x": 710, "y": 77}, {"x": 694, "y": 77}]}, "text": "l"}]}]}], "blockType": "TEXT"}, {"boundingBox": {"vertices": [{"x": 845, "y": 58}, {"x": 1086, "y": 57}, {"x": 1086, "y": 113}, {"x": 845, "y": 114}]}, "paragraphs": [{"boundingBox": {"vertices": [{"x": 845, "y": 58}, {"x": 1086, "y": 57}, {"x": 1086, "y": 113}, {"x": 845, "y": 114}]}, "words": [{"boundingBox": {"vertices": [{"x": 845, "y": 58}, {"x": 1086, "y": 57}, {"x": 1086, "y": 113}, {"x": 845, "y": 114}]}, "symbols": [{"boundingBox": {"vertices": [{"x": 845, "y": 59}, {"x": 887, "y": 59}, {"x": 887, "y": 114}, {"x": 845, "y": 114}]}, "text": "1"}, {"boundingBox": {"vertices": [{"x": 882, "y": 58}, {"x": 921, "y": 58}, {"x": 921, "y": 113}, {"x": 882, "y": 113}]}, "text": "0"}, {"boundingBox": {"vertices": [{"x": 927, "y": 58}, {"x": 966, "y": 58}, {"x": 966, "y": 113}, {"x": 927, "y": 113}]}, "text": "6"}, {"boundingBox": {"vertices": [{"x": 977, "y": 58}, {"x": 1012, "y": 58}, {"x": 1012, "y": 113}, {"x": 977, "y": 113}]}, "text": "2"}, {"boundingBox": {"vertices": [{"x": 1018, "y": 58}, {"x": 1054, "y": 58}, {"x": 1054, "y": 113}, {"x": 1018, "y": 113}]}, "text": "0"}, {"property": {"detectedBreak": {"type": "LINE_BREAK"}}, "boundingBox": {"vertices": [{"x": 1062, "y": 57}, {"x": 1086, "y": 57}, {"x": 1086, "y": 112}, {"x": 1062, "y": 112}]}, "text": "3"}]}]}], "blockType": "TEXT"}, {"boundingBox": {"vertices": [{"x": 261, "y": 126}, {"x": 1127, "y": 136}, {"x": 1127, "y": 166}, {"x": 261, "y": 156}]}, "paragraphs": [{"boundingBox": {"vertices": [{"x": 261, "y": 126}, {"x": 1127, "y": 136}, {"x": 1127, "y": 166}, {"x": 261, "y": 156}]}, "words": [{"property": {"detectedLanguages": [{"languageCode": "en", "confidence": 1}]}, "boundingBox": {"vertices": [{"x": 261, "y": 126}, {"x": 372, "y": 127}, {"x": 372, "y": 157}, {"x": 261, "y": 156}]}, "symbols": [{"boundingBox": {"vertices": [{"x": 261, "y": 127}, {"x": 279, "y": 127}, {"x": 279, "y": 156}, {"x": 261, "y": 156}]}, "text": "J"}, {"boundingBox": {"vertices": [{"x": 280, "y": 127}, {"x": 297, "y": 127}, {"x": 297, "y": 156}, {"x": 280, "y": 156}]}, "text": "u"}, {"boundingBox": {"vertices": [{"x": 298, "y": 127}, {"x": 315, "y": 127}, {"x": 315, "y": 156}, {"x": 298, "y": 156}]}, "text": "l"}, {"boundingBox": {"vertices": [{"x": 317, "y": 127}, {"x": 334, "y": 127}, {"x": 334, "y": 156}, {"x": 317, "y": 156}]}, "text": "i"}, {"boundingBox": {"vertices": [{"x": 336, "y": 127}, {"x": 353, "y": 127}, {"x": 353, "y": 156}, {"x": 336, "y": 156}]}, "text": "u"}, {"property": {"detectedBreak": {"type": "SPACE"}}, "boundingBox": {"vertices": [{"x": 355, "y": 128}, {"x": 372, "y": 128}, {"x": 372, "y": 157}, {"x": 355, "y": 157}]}, "text": "s"}]}, {"property": {"detectedLanguages": [{"languageCode": "en", "confidence": 1}]}, "boundingBox": {"vertices": [{"x": 392, "y": 128}, {"x": 408, "y": 128}, {"x": 408, "y": 157}, {"x": 392, "y": 157}]}, "symbols": [{"boundingBox": {"vertices": [{"x": 392, "y": 128}, {"x": 408, "y": 128}, {"x": 408, "y": 157}, {"x": 392, "y": 157}]}, "text": "u"}]}, {"property": {"detectedLanguages": [{"languageCode": "en", "confidence": 1}]}, "boundingBox": {"vertices": [{"x": 414, "y": 128}, {"x": 423, "y": 128}, {"x": 423, "y": 157}, {"x": 414, "y": 157}]}, "symbols": [{"property": {"detectedBreak": {"type": "SPACE"}}, "boundingBox": {"vertices": [{"x": 414, "y": 128}, {"x": 423, "y": 128}, {"x": 423, "y": 157}, {"x": 414, "y": 157}]}, "text": "."}]}, {"property": {"detectedLanguages": [{"languageCode": "en", "confidence": 1}]}, "boundingBox": {"vertices": [{"x": 447, "y": 128}, {"x": 598, "y": 130}, {"x": 598, "y": 160}, {"x": 447, "y": 158}]}, "symbols": [{"boundingBox": {"vertices": [{"x": 447, "y": 129}, {"x": 465, "y": 129}, {"x": 465, "y": 158}, {"x": 447, "y": 158}]}, "text": "M"}, {"boundingBox": {"vertices": [{"x": 468, "y": 129}, {"x": 484, "y": 129}, {"x": 484, "y": 158}, {"x": 468, "y": 158}]}, "text": "a"}, {"boundingBox": {"vertices": [{"x": 485, "y": 129}, {"x": 502, "y": 129}, {"x": 502, "y": 158}, {"x": 485, "y": 158}]}, "text": "t"}, {"boundingBox": {"vertices": [{"x": 504, "y": 129}, {"x": 521, "y": 129}, {"x": 521, "y": 158}, {"x": 504, "y": 158}]}, "text": "h"}, {"boundingBox": {"vertices": [{"x": 523, "y": 129}, {"x": 540, "y": 129}, {"x": 540, "y": 158}, {"x": 523, "y": 158}]}, "text": "i"}, {"boundingBox": {"vertices": [{"x": 542, "y": 130}, {"x": 560, "y": 130}, {"x": 560, "y": 159}, {"x": 542, "y": 159}]}, "text": "l"}, {"boundingBox": {"vertices": [{"x": 561, "y": 130}, {"x": 576, "y": 130}, {"x": 576, "y": 159}, {"x": 561, "y": 159}]}, "text": "d"}, {"property": {"detectedBreak": {"type": "SPACE"}}, "boundingBox": {"vertices": [{"x": 580, "y": 130}, {"x": 598, "y": 130}, {"x": 598, "y": 159}, {"x": 580, "y": 159}]}, "text": "e"}]}, {"property": {"detectedLanguages": [{"languageCode": "en", "confidence": 1}]}, "boundingBox": {"vertices": [{"x": 617, "y": 130}, {"x": 785, "y": 132}, {"x": 785, "y": 162}, {"x": 617, "y": 160}]}, "symbols": [{"boundingBox": {"vertices": [{"x": 617, "y": 130}, {"x": 633, "y": 130}, {"x": 633, "y": 159}, {"x": 617, "y": 159}]}, "text": "E"}, {"boundingBox": {"vertices": [{"x": 635, "y": 131}, {"x": 654, "y": 131}, {"x": 654, "y": 160}, {"x": 635, "y": 160}]}, "text": "l"}, {"boundingBox": {"vertices": [{"x": 655, "y": 131}, {"x": 673, "y": 131}, {"x": 673, "y": 160}, {"x": 655, "y": 160}]}, "text": "i"}, {"boundingBox": {"vertices": [{"x": 674, "y": 131}, {"x": 690, "y": 131}, {"x": 690, "y": 160}, {"x": 674, "y": 160}]}, "text": "s"}, {"boundingBox": {"vertices": [{"x": 694, "y": 131}, {"x": 709, "y": 131}, {"x": 709, "y": 160}, {"x": 694, "y": 160}]}, "text": "a"}, {"boundingBox": {"vertices": [{"x": 711, "y": 131}, {"x": 728, "y": 131}, {"x": 728, "y": 160}, {"x": 711, "y": 160}]}, "text": "b"}, {"boundingBox": {"vertices": [{"x": 731, "y": 132}, {"x": 747, "y": 132}, {"x": 747, "y": 161}, {"x": 731, "y": 161}]}, "text": "e"}, {"boundingBox": {"vertices": [{"x": 748, "y": 132}, {"x": 765, "y": 132}, {"x": 765, "y": 161}, {"x": 748, "y": 161}]}, "text": "t"}, {"property": {"detectedBreak": {"type": "SPACE"}}, "boundingBox": {"vertices": [{"x": 768, "y": 132}, {"x": 785, "y": 132}, {"x": 785, "y": 161}, {"x": 768, "y": 161}]}, "text": "h"}]}, {"property": {"detectedLanguages": [{"languageCode": "en", "confidence": 1}]}, "boundingBox": {"vertices": [{"x": 805, "y": 132}, {"x": 974, "y": 134}, {"x": 974, "y": 164}, {"x": 805, "y": 162}]}, "symbols": [{"boundingBox": {"vertices": [{"x": 805, "y": 133}, {"x": 825, "y": 133}, {"x": 825, "y": 162}, {"x": 805, "y": 162}]}, "text": "W"}, {"boundingBox": {"vertices": [{"x": 825, "y": 133}, {"x": 843, "y": 133}, {"x": 843, "y": 162}, {"x": 825, "y": 162}]}, "text": "i"}, {"boundingBox": {"vertices": [{"x": 844, "y": 133}, {"x": 861, "y": 133}, {"x": 861, "y": 162}, {"x": 844, "y": 162}]}, "text": "l"}, {"boundingBox": {"vertices": [{"x": 864, "y": 133}, {"x": 879, "y": 133}, {"x": 879, "y": 162}, {"x": 864, "y": 162}]}, "text": "h"}, {"boundingBox": {"vertices": [{"x": 882, "y": 133}, {"x": 898, "y": 133}, {"x": 898, "y": 162}, {"x": 882, "y": 162}]}, "text": "e"}, {"boundingBox": {"vertices": [{"x": 901, "y": 134}, {"x": 919, "y": 134}, {"x": 919, "y": 163}, {"x": 901, "y": 163}]}, "text": "l"}, {"boundingBox": {"vertices": [{"x": 919, "y": 134}, {"x": 937, "y": 134}, {"x": 937, "y": 163}, {"x": 919, "y": 163}]}, "text": "m"}, {"boundingBox": {"vertices": [{"x": 940, "y": 134}, {"x": 957, "y": 134}, {"x": 957, "y": 163}, {"x": 940, "y": 163}]}, "text": "i"}, {"property": {"detectedBreak": {"type": "SPACE"}}, "boundingBox": {"vertices": [{"x": 959, "y": 134}, {"x": 974, "y": 134}, {"x": 974, "y": 163}, {"x": 959, "y": 163}]}, "text": "n"}]}, {"property": {"detectedLanguages": [{"languageCode": "en", "confidence": 1}]}, "boundingBox": {"vertices": [{"x": 997, "y": 134}, {"x": 1127, "y": 135}, {"x": 1127, "y": 165}, {"x": 997, "y": 164}]}, "symbols": [{"boundingBox": {"vertices": [{"x": 997, "y": 135}, {"x": 1013, "y": 135}, {"x": 1013, "y": 164}, {"x": 997, "y": 164}]}, "text": "R"}, {"boundingBox": {"vertices": [{"x": 1014, "y": 135}, {"x": 1031, "y": 135}, {"x": 1031, "y": 164}, {"x": 1014, "y": 164}]}, "text": "U"}, {"boundingBox": {"vertices": [{"x": 1034, "y": 135}, {"x": 1051, "y": 135}, {"x": 1051, "y": 164}, {"x": 1034, "y": 164}]}, "text": "D"}, {"boundingBox": {"vertices": [{"x": 1053, "y": 135}, {"x": 1070, "y": 135}, {"x": 1070, "y": 164}, {"x": 1053, "y": 164}]}, "text": "O"}, {"boundingBox": {"vertices": [{"x": 1072, "y": 135}, {"x": 1091, "y": 135}, {"x": 1091, "y": 164}, {"x": 1072, "y": 164}]}, "text": "L"}, {"boundingBox": {"vertices": [{"x": 1091, "y": 136}, {"x": 1109, "y": 136}, {"x": 1109, "y": 165}, {"x": 1091, "y": 165}]}, "text": "P"}, {"property": {"detectedBreak": {"type": "LINE_BREAK"}}, "boundingBox": {"vertices": [{"x": 1109, "y": 136}, {"x": 1127, "y": 136}, {"x": 1127, "y": 165}, {"x": 1109, "y": 165}]}, "text": "H"}]}]}], "blockType": "TEXT"}, {"boundingBox": {"vertices": [{"x": 12, "y": 354}, {"x": 144, "y": 355}, {"x": 144, "y": 381}, {"x": 12, "y": 380}]}, "paragraphs": [{"boundingBox": {"vertices": [{"x": 12, "y": 354}, {"x": 144, "y": 355}, {"x": 144, "y": 381}, {"x": 12, "y": 380}]}, "words": [{"boundingBox": {"vertices": [{"x": 12, "y": 354}, {"x": 144, "y": 355}, {"x": 144, "y": 381}, {"x": 12, "y": 380}]}, "symbols": [{"boundingBox": {"vertices": [{"x": 12, "y": 355}, {"x": 29, "y": 355}, {"x": 29, "y": 380}, {"x": 12, "y": 380}]}, "text": "1"}, {"boundingBox": {"vertices": [{"x": 31, "y": 355}, {"x": 48, "y": 355}, {"x": 48, "y": 380}, {"x": 31, "y": 380}]}, "text": "7"}, {"boundingBox": {"vertices": [{"x": 55, "y": 355}, {"x": 65, "y": 355}, {"x": 65, "y": 380}, {"x": 55, "y": 380}]}, "text": "."}, {"boundingBox": {"vertices": [{"x": 69, "y": 355}, {"x": 89, "y": 355}, {"x": 89, "y": 380}, {"x": 69, "y": 380}]}, "text": "6"}, {"boundingBox": {"vertices": [{"x": 92, "y": 355}, {"x": 102, "y": 355}, {"x": 102, "y": 380}, {"x": 92, "y": 380}]}, "text": "."}, {"boundingBox": {"vertices": [{"x": 105, "y": 355}, {"x": 124, "y": 355}, {"x": 124, "y": 380}, {"x": 105, "y": 380}]}, "text": "4"}, {"property": {"detectedBreak": {"type": "LINE_BREAK"}}, "boundingBox": {"vertices": [{"x": 126, "y": 355}, {"x": 144, "y": 355}, {"x": 144, "y": 380}, {"x": 126, "y": 380}]}, "text": "3"}]}]}], "blockType": "TEXT"}, {"boundingBox": {"vertices": [{"x": 258, "y": 242}, {"x": 502, "y": 244}, {"x": 502, "y": 271}, {"x": 258, "y": 269}]}, "paragraphs": [{"boundingBox": {"vertices": [{"x": 258, "y": 242}, {"x": 502, "y": 244}, {"x": 502, "y": 271}, {"x": 258, "y": 269}]}, "words": [{"boundingBox": {"vertices": [{"x": 258, "y": 243}, {"x": 334, "y": 244}, {"x": 334, "y": 270}, {"x": 258, "y": 269}]}, "symbols": [{"boundingBox": {"vertices": [{"x": 258, "y": 243}, {"x": 276, "y": 243}, {"x": 276, "y": 269}, {"x": 258, "y": 269}]}, "text": "R"}, {"boundingBox": {"vertices": [{"x": 279, "y": 243}, {"x": 296, "y": 243}, {"x": 296, "y": 269}, {"x": 279, "y": 269}]}, "text": "e"}, {"boundingBox": {"vertices": [{"x": 298, "y": 243}, {"x": 314, "y": 243}, {"x": 314, "y": 269}, {"x": 298, "y": 269}]}, "text": "s"}, {"property": {"detectedBreak": {"type": "SPACE"}}, "boundingBox": {"vertices": [{"x": 315, "y": 243}, {"x": 334, "y": 243}, {"x": 334, "y": 269}, {"x": 315, "y": 269}]}, "text": "i"}]}, {"boundingBox": {"vertices": [{"x": 353, "y": 243}, {"x": 502, "y": 244}, {"x": 502, "y": 271}, {"x": 353, "y": 270}]}, "symbols": [{"boundingBox": {"vertices": [{"x": 353, "y": 243}, {"x": 371, "y": 243}, {"x": 371, "y": 269}, {"x": 353, "y": 269}]}, "text": "M"}, {"boundingBox": {"vertices": [{"x": 372, "y": 243}, {"x": 389, "y": 243}, {"x": 389, "y": 269}, {"x": 372, "y": 269}]}, "text": "a"}, {"boundingBox": {"vertices": [{"x": 390, "y": 244}, {"x": 407, "y": 244}, {"x": 407, "y": 270}, {"x": 390, "y": 270}]}, "text": "r"}, {"boundingBox": {"vertices": [{"x": 410, "y": 244}, {"x": 427, "y": 244}, {"x": 427, "y": 270}, {"x": 410, "y": 270}]}, "text": "k"}, {"boundingBox": {"vertices": [{"x": 428, "y": 244}, {"x": 445, "y": 244}, {"x": 445, "y": 270}, {"x": 428, "y": 270}]}, "text": "h"}, {"boundingBox": {"vertices": [{"x": 447, "y": 244}, {"x": 466, "y": 244}, {"x": 466, "y": 270}, {"x": 447, "y": 270}]}, "text": "o"}, {"boundingBox": {"vertices": [{"x": 466, "y": 244}, {"x": 485, "y": 244}, {"x": 485, "y": 270}, {"x": 466, "y": 270}]}, "text": "f"}, {"property": {"detectedBreak": {"type": "LINE_BREAK"}}, "boundingBox": {"vertices": [{"x": 484, "y": 244}, {"x": 502, "y": 244}, {"x": 502, "y": 270}, {"x": 484, "y": 270}]}, "text": "f"}]}]}], "blockType": "TEXT"}, {"boundingBox": {"vertices": [{"x": 257, "y": 317}, {"x": 614, "y": 320}, {"x": 613, "y": 385}, {"x": 256, "y": 382}]}, "paragraphs": [{"boundingBox": {"vertices": [{"x": 259, "y": 317}, {"x": 578, "y": 320}, {"x": 578, "y": 348}, {"x": 259, "y": 345}]}, "words": [{"property": {"detectedLanguages": [{"languageCode": "en", "confidence": 1}]}, "boundingBox": {"vertices": [{"x": 259, "y": 317}, {"x": 445, "y": 319}, {"x": 445, "y": 347}, {"x": 259, "y": 345}]}, "symbols": [{"boundingBox": {"vertices": [{"x": 259, "y": 318}, {"x": 277, "y": 318}, {"x": 277, "y": 345}, {"x": 259, "y": 345}]}, "text": "1"}, {"boundingBox": {"vertices": [{"x": 278, "y": 318}, {"x": 295, "y": 318}, {"x": 295, "y": 345}, {"x": 278, "y": 345}]}, "text": "8"}, {"boundingBox": {"vertices": [{"x": 301, "y": 318}, {"x": 309, "y": 318}, {"x": 309, "y": 345}, {"x": 301, "y": 345}]}, "text": "."}, {"boundingBox": {"vertices": [{"x": 316, "y": 318}, {"x": 333, "y": 318}, {"x": 333, "y": 345}, {"x": 316, "y": 345}]}, "text": "1"}, {"boundingBox": {"vertices": [{"x": 334, "y": 318}, {"x": 351, "y": 318}, {"x": 351, "y": 345}, {"x": 334, "y": 345}]}, "text": "2"}, {"boundingBox": {"vertices": [{"x": 359, "y": 318}, {"x": 367, "y": 318}, {"x": 367, "y": 345}, {"x": 359, "y": 345}]}, "text": "."}, {"boundingBox": {"vertices": [{"x": 372, "y": 318}, {"x": 389, "y": 318}, {"x": 389, "y": 345}, {"x": 372, "y": 345}]}, "text": "1"}, {"boundingBox": {"vertices": [{"x": 391, "y": 319}, {"x": 407, "y": 319}, {"x": 407, "y": 346}, {"x": 391, "y": 346}]}, "text": "9"}, {"boundingBox": {"vertices": [{"x": 410, "y": 319}, {"x": 427, "y": 319}, {"x": 427, "y": 346}, {"x": 410, "y": 346}]}, "text": "1"}, {"property": {"detectedBreak": {"type": "SPACE"}}, "boundingBox": {"vertices": [{"x": 428, "y": 319}, {"x": 445, "y": 319}, {"x": 445, "y": 346}, {"x": 428, "y": 346}]}, "text": "4"}]}, {"property": {"detectedLanguages": [{"languageCode": "en", "confidence": 1}]}, "boundingBox": {"vertices": [{"x": 464, "y": 319}, {"x": 578, "y": 320}, {"x": 578, "y": 348}, {"x": 464, "y": 347}]}, "symbols": [{"boundingBox": {"vertices": [{"x": 464, "y": 319}, {"x": 481, "y": 319}, {"x": 481, "y": 346}, {"x": 464, "y": 346}]}, "text": "B"}, {"boundingBox": {"vertices": [{"x": 484, "y": 319}, {"x": 500, "y": 319}, {"x": 500, "y": 346}, {"x": 484, "y": 346}]}, "text": "e"}, {"boundingBox": {"vertices": [{"x": 503, "y": 320}, {"x": 521, "y": 320}, {"x": 521, "y": 347}, {"x": 503, "y": 347}]}, "text": "r"}, {"boundingBox": {"vertices": [{"x": 523, "y": 320}, {"x": 540, "y": 320}, {"x": 540, "y": 347}, {"x": 523, "y": 347}]}, "text": "l"}, {"boundingBox": {"vertices": [{"x": 541, "y": 320}, {"x": 558, "y": 320}, {"x": 558, "y": 347}, {"x": 541, "y": 347}]}, "text": "i"}, {"property": {"detectedBreak": {"type": "LINE_BREAK"}}, "boundingBox": {"vertices": [{"x": 559, "y": 320}, {"x": 578, "y": 320}, {"x": 578, "y": 347}, {"x": 559, "y": 347}]}, "text": "n"}]}]}, {"boundingBox": {"vertices": [{"x": 257, "y": 355}, {"x": 614, "y": 358}, {"x": 614, "y": 385}, {"x": 257, "y": 382}]}, "words": [{"property": {"detectedLanguages": [{"languageCode": "de", "confidence": 1}]}, "boundingBox": {"vertices": [{"x": 257, "y": 356}, {"x": 276, "y": 356}, {"x": 276, "y": 382}, {"x": 257, "y": 382}]}, "symbols": [{"boundingBox": {"vertices": [{"x": 257, "y": 356}, {"x": 276, "y": 356}, {"x": 276, "y": 382}, {"x": 257, "y": 382}]}, "text": "i"}]}, {"property": {"detectedLanguages": [{"languageCode": "de", "confidence": 1}]}, "boundingBox": {"vertices": [{"x": 282, "y": 356}, {"x": 293, "y": 356}, {"x": 293, "y": 382}, {"x": 282, "y": 382}]}, "symbols": [{"property": {"detectedBreak": {"type": "SPACE"}}, "boundingBox": {"vertices": [{"x": 282, "y": 356}, {"x": 293, "y": 356}, {"x": 293, "y": 382}, {"x": 282, "y": 382}]}, "text": "."}]}, {"property": {"detectedLanguages": [{"languageCode": "de", "confidence": 1}]}, "boundingBox": {"vertices": [{"x": 316, "y": 356}, {"x": 426, "y": 357}, {"x": 426, "y": 383}, {"x": 316, "y": 382}]}, "symbols": [{"boundingBox": {"vertices": [{"x": 316, "y": 356}, {"x": 332, "y": 356}, {"x": 332, "y": 382}, {"x": 316, "y": 382}]}, "text": "B"}, {"boundingBox": {"vertices": [{"x": 334, "y": 356}, {"x": 351, "y": 356}, {"x": 351, "y": 382}, {"x": 334, "y": 382}]}, "text": "e"}, {"boundingBox": {"vertices": [{"x": 352, "y": 356}, {"x": 372, "y": 356}, {"x": 372, "y": 382}, {"x": 352, "y": 382}]}, "text": "r"}, {"boundingBox": {"vertices": [{"x": 371, "y": 357}, {"x": 390, "y": 357}, {"x": 390, "y": 383}, {"x": 371, "y": 383}]}, "text": "l"}, {"boundingBox": {"vertices": [{"x": 390, "y": 357}, {"x": 410, "y": 357}, {"x": 410, "y": 383}, {"x": 390, "y": 383}]}, "text": "i"}, {"property": {"detectedBreak": {"type": "SPACE"}}, "boundingBox": {"vertices": [{"x": 409, "y": 357}, {"x": 426, "y": 357}, {"x": 426, "y": 383}, {"x": 409, "y": 383}]}, "text": "n"}]}, {"property": {"detectedLanguages": [{"languageCode": "de", "confidence": 1}]}, "boundingBox": {"vertices": [{"x": 447, "y": 357}, {"x": 614, "y": 359}, {"x": 614, "y": 386}, {"x": 447, "y": 384}]}, "symbols": [{"boundingBox": {"vertices": [{"x": 447, "y": 357}, {"x": 464, "y": 357}, {"x": 464, "y": 383}, {"x": 447, "y": 383}]}, "text": "v"}, {"boundingBox": {"vertices": [{"x": 466, "y": 357}, {"x": 483, "y": 357}, {"x": 483, "y": 383}, {"x": 466, "y": 383}]}, "text": "e"}, {"boundingBox": {"vertices": [{"x": 485, "y": 358}, {"x": 502, "y": 358}, {"x": 502, "y": 384}, {"x": 485, "y": 384}]}, "text": "r"}, {"boundingBox": {"vertices": [{"x": 502, "y": 358}, {"x": 520, "y": 358}, {"x": 520, "y": 384}, {"x": 502, "y": 384}]}, "text": "h"}, {"boundingBox": {"vertices": [{"x": 524, "y": 358}, {"x": 540, "y": 358}, {"x": 540, "y": 384}, {"x": 524, "y": 384}]}, "text": "a"}, {"boundingBox": {"vertices": [{"x": 541, "y": 358}, {"x": 558, "y": 358}, {"x": 558, "y": 384}, {"x": 541, "y": 384}]}, "text": "f"}, {"boundingBox": {"vertices": [{"x": 559, "y": 358}, {"x": 576, "y": 358}, {"x": 576, "y": 384}, {"x": 559, "y": 384}]}, "text": "t"}, {"boundingBox": {"vertices": [{"x": 579, "y": 358}, {"x": 596, "y": 358}, {"x": 596, "y": 384}, {"x": 579, "y": 384}]}, "text": "e"}, {"property": {"detectedBreak": {"type": "LINE_BREAK"}}, "boundingBox": {"vertices": [{"x": 597, "y": 359}, {"x": 614, "y": 359}, {"x": 614, "y": 385}, {"x": 597, "y": 385}]}, "text": "t"}]}]}], "blockType": "TEXT"}, {"boundingBox": {"vertices": [{"x": 900, "y": 251}, {"x": 1032, "y": 253}, {"x": 1031, "y": 316}, {"x": 899, "y": 314}]}, "paragraphs": [{"boundingBox": {"vertices": [{"x": 900, "y": 251}, {"x": 1032, "y": 253}, {"x": 1031, "y": 316}, {"x": 899, "y": 314}]}, "words": [{"boundingBox": {"vertices": [{"x": 900, "y": 252}, {"x": 935, "y": 253}, {"x": 934, "y": 278}, {"x": 899, "y": 277}]}, "symbols": [{"boundingBox": {"vertices": [{"x": 900, "y": 252}, {"x": 916, "y": 252}, {"x": 915, "y": 277}, {"x": 899, "y": 277}]}, "text": "i"}, {"boundingBox": {"vertices": [{"x": 919, "y": 252}, {"x": 935, "y": 252}, {"x": 934, "y": 277}, {"x": 918, "y": 277}]}, "text": "s"}]}, {"boundingBox": {"vertices": [{"x": 943, "y": 252}, {"x": 952, "y": 252}, {"x": 951, "y": 277}, {"x": 942, "y": 277}]}, "symbols": [{"property": {"detectedBreak": {"type": "EOL_SURE_SPACE"}}, "boundingBox": {"vertices": [{"x": 943, "y": 252}, {"x": 952, "y": 252}, {"x": 951, "y": 277}, {"x": 942, "y": 277}]}, "text": "."}]}, {"property": {"detectedLanguages": [{"languageCode": "de", "confidence": 1}]}, "boundingBox": {"vertices": [{"x": 900, "y": 289}, {"x": 1031, "y": 291}, {"x": 1031, "y": 316}, {"x": 900, "y": 314}]}, "symbols": [{"boundingBox": {"vertices": [{"x": 900, "y": 290}, {"x": 916, "y": 290}, {"x": 916, "y": 314}, {"x": 900, "y": 314}]}, "text": "d"}, {"boundingBox": {"vertices": [{"x": 920, "y": 290}, {"x": 935, "y": 290}, {"x": 935, "y": 314}, {"x": 920, "y": 314}]}, "text": "e"}, {"boundingBox": {"vertices": [{"x": 939, "y": 290}, {"x": 954, "y": 290}, {"x": 954, "y": 314}, {"x": 939, "y": 314}]}, "text": "u"}, {"boundingBox": {"vertices": [{"x": 956, "y": 290}, {"x": 972, "y": 290}, {"x": 972, "y": 314}, {"x": 956, "y": 314}]}, "text": "t"}, {"boundingBox": {"vertices": [{"x": 976, "y": 290}, {"x": 991, "y": 290}, {"x": 991, "y": 314}, {"x": 976, "y": 314}]}, "text": "s"}, {"boundingBox": {"vertices": [{"x": 995, "y": 291}, {"x": 1010, "y": 291}, {"x": 1010, "y": 315}, {"x": 995, "y": 315}]}, "text": "c"}, {"property": {"detectedBreak": {"type": "LINE_BREAK"}}, "boundingBox": {"vertices": [{"x": 1013, "y": 291}, {"x": 1031, "y": 291}, {"x": 1031, "y": 315}, {"x": 1013, "y": 315}]}, "text": "h"}]}]}], "blockType": "TEXT"}, {"boundingBox": {"vertices": [{"x": 11, "y": 389}, {"x": 1067, "y": 398}, {"x": 1066, "y": 547}, {"x": 10, "y": 538}]}, "paragraphs": [{"boundingBox": {"vertices": [{"x": 11, "y": 389}, {"x": 1067, "y": 399}, {"x": 1066, "y": 514}, {"x": 10, "y": 504}]}, "words": [{"boundingBox": {"vertices": [{"x": 11, "y": 392}, {"x": 181, "y": 393}, {"x": 181, "y": 420}, {"x": 11, "y": 419}]}, "symbols": [{"boundingBox": {"vertices": [{"x": 11, "y": 393}, {"x": 28, "y": 393}, {"x": 28, "y": 419}, {"x": 11, "y": 419}]}, "text": "2"}, {"boundingBox": {"vertices": [{"x": 30, "y": 393}, {"x": 48, "y": 393}, {"x": 48, "y": 419}, {"x": 30, "y": 419}]}, "text": "9"}, {"boundingBox": {"vertices": [{"x": 55, "y": 393}, {"x": 65, "y": 393}, {"x": 65, "y": 419}, {"x": 55, "y": 419}]}, "text": "."}, {"boundingBox": {"vertices": [{"x": 68, "y": 393}, {"x": 86, "y": 393}, {"x": 86, "y": 419}, {"x": 68, "y": 419}]}, "text": "6"}, {"boundingBox": {"vertices": [{"x": 92, "y": 393}, {"x": 103, "y": 393}, {"x": 103, "y": 419}, {"x": 92, "y": 419}]}, "text": "."}, {"boundingBox": {"vertices": [{"x": 106, "y": 393}, {"x": 123, "y": 393}, {"x": 123, "y": 419}, {"x": 106, "y": 419}]}, "text": "1"}, {"boundingBox": {"vertices": [{"x": 126, "y": 393}, {"x": 142, "y": 393}, {"x": 142, "y": 419}, {"x": 126, "y": 419}]}, "text": "9"}, {"boundingBox": {"vertices": [{"x": 145, "y": 393}, {"x": 163, "y": 393}, {"x": 163, "y": 419}, {"x": 145, "y": 419}]}, "text": "4"}, {"property": {"detectedBreak": {"type": "SPACE"}}, "boundingBox": {"vertices": [{"x": 164, "y": 393}, {"x": 181, "y": 393}, {"x": 181, "y": 419}, {"x": 164, "y": 419}]}, "text": "3"}]}, {"boundingBox": {"vertices": [{"x": 260, "y": 393}, {"x": 277, "y": 393}, {"x": 277, "y": 423}, {"x": 260, "y": 423}]}, "symbols": [{"boundingBox": {"vertices": [{"x": 260, "y": 393}, {"x": 277, "y": 393}, {"x": 277, "y": 423}, {"x": 260, "y": 423}]}, "text": "n"}]}, {"boundingBox": {"vertices": [{"x": 283, "y": 393}, {"x": 292, "y": 393}, {"x": 292, "y": 423}, {"x": 283, "y": 423}]}, "symbols": [{"property": {"detectedBreak": {"type": "SPACE"}}, "boundingBox": {"vertices": [{"x": 283, "y": 393}, {"x": 292, "y": 393}, {"x": 292, "y": 423}, {"x": 283, "y": 423}]}, "text": "."}]}, {"boundingBox": {"vertices": [{"x": 314, "y": 393}, {"x": 577, "y": 397}, {"x": 577, "y": 428}, {"x": 314, "y": 424}]}, "symbols": [{"boundingBox": {"vertices": [{"x": 314, "y": 393}, {"x": 334, "y": 393}, {"x": 334, "y": 423}, {"x": 314, "y": 423}]}, "text": "T"}, {"boundingBox": {"vertices": [{"x": 335, "y": 394}, {"x": 351, "y": 394}, {"x": 351, "y": 424}, {"x": 335, "y": 424}]}, "text": "h"}, {"boundingBox": {"vertices": [{"x": 353, "y": 394}, {"x": 370, "y": 394}, {"x": 370, "y": 424}, {"x": 353, "y": 424}]}, "text": "e"}, {"boundingBox": {"vertices": [{"x": 371, "y": 394}, {"x": 388, "y": 394}, {"x": 388, "y": 424}, {"x": 371, "y": 424}]}, "text": "r"}, {"boundingBox": {"vertices": [{"x": 392, "y": 394}, {"x": 408, "y": 394}, {"x": 408, "y": 424}, {"x": 392, "y": 424}]}, "text": "e"}, {"boundingBox": {"vertices": [{"x": 411, "y": 395}, {"x": 427, "y": 395}, {"x": 427, "y": 425}, {"x": 411, "y": 425}]}, "text": "s"}, {"boundingBox": {"vertices": [{"x": 429, "y": 395}, {"x": 445, "y": 395}, {"x": 445, "y": 425}, {"x": 429, "y": 425}]}, "text": "i"}, {"boundingBox": {"vertices": [{"x": 448, "y": 395}, {"x": 464, "y": 395}, {"x": 464, "y": 425}, {"x": 448, "y": 425}]}, "text": "e"}, {"boundingBox": {"vertices": [{"x": 467, "y": 396}, {"x": 482, "y": 396}, {"x": 482, "y": 426}, {"x": 467, "y": 426}]}, "text": "n"}, {"boundingBox": {"vertices": [{"x": 485, "y": 396}, {"x": 501, "y": 396}, {"x": 501, "y": 426}, {"x": 485, "y": 426}]}, "text": "s"}, {"boundingBox": {"vertices": [{"x": 503, "y": 396}, {"x": 521, "y": 396}, {"x": 521, "y": 426}, {"x": 503, "y": 426}]}, "text": "t"}, {"boundingBox": {"vertices": [{"x": 523, "y": 396}, {"x": 539, "y": 396}, {"x": 539, "y": 426}, {"x": 523, "y": 426}]}, "text": "a"}, {"boundingBox": {"vertices": [{"x": 541, "y": 397}, {"x": 557, "y": 397}, {"x": 557, "y": 427}, {"x": 541, "y": 427}]}, "text": "d"}, {"property": {"detectedBreak": {"type": "SPACE"}}, "boundingBox": {"vertices": [{"x": 559, "y": 397}, {"x": 577, "y": 397}, {"x": 577, "y": 427}, {"x": 559, "y": 427}]}, "text": "t"}]}, {"boundingBox": {"vertices": [{"x": 597, "y": 397}, {"x": 748, "y": 399}, {"x": 748, "y": 430}, {"x": 597, "y": 428}]}, "symbols": [{"boundingBox": {"vertices": [{"x": 597, "y": 397}, {"x": 613, "y": 397}, {"x": 613, "y": 427}, {"x": 597, "y": 427}]}, "text": "ü"}, {"boundingBox": {"vertices": [{"x": 616, "y": 398}, {"x": 632, "y": 398}, {"x": 632, "y": 428}, {"x": 616, "y": 428}]}, "text": "b"}, {"boundingBox": {"vertices": [{"x": 636, "y": 398}, {"x": 653, "y": 398}, {"x": 653, "y": 428}, {"x": 636, "y": 428}]}, "text": "e"}, {"boundingBox": {"vertices": [{"x": 655, "y": 398}, {"x": 673, "y": 398}, {"x": 673, "y": 428}, {"x": 655, "y": 428}]}, "text": "r"}, {"boundingBox": {"vertices": [{"x": 673, "y": 399}, {"x": 690, "y": 399}, {"x": 690, "y": 429}, {"x": 673, "y": 429}]}, "text": "s"}, {"boundingBox": {"vertices": [{"x": 691, "y": 399}, {"x": 709, "y": 399}, {"x": 709, "y": 429}, {"x": 691, "y": 429}]}, "text": "t"}, {"boundingBox": {"vertices": [{"x": 715, "y": 399}, {"x": 725, "y": 399}, {"x": 725, "y": 429}, {"x": 715, "y": 429}]}, "text": "."}, {"boundingBox": {"vertices": [{"x": 731, "y": 399}, {"x": 748, "y": 399}, {"x": 748, "y": 429}, {"x": 731, "y": 429}]}, "text": "i"}]}, {"boundingBox": {"vertices": [{"x": 750, "y": 400}, {"x": 765, "y": 400}, {"x": 765, "y": 430}, {"x": 750, "y": 430}]}, "symbols": [{"boundingBox": {"vertices": [{"x": 750, "y": 400}, {"x": 765, "y": 400}, {"x": 765, "y": 430}, {"x": 750, "y": 430}]}, "text": "/"}]}, {"boundingBox": {"vertices": [{"x": 767, "y": 399}, {"x": 916, "y": 401}, {"x": 916, "y": 432}, {"x": 767, "y": 430}]}, "symbols": [{"boundingBox": {"vertices": [{"x": 767, "y": 400}, {"x": 783, "y": 400}, {"x": 783, "y": 430}, {"x": 767, "y": 430}]}, "text": "9"}, {"boundingBox": {"vertices": [{"x": 786, "y": 400}, {"x": 802, "y": 400}, {"x": 802, "y": 430}, {"x": 786, "y": 430}]}, "text": "7"}, {"boundingBox": {"vertices": [{"x": 807, "y": 400}, {"x": 822, "y": 400}, {"x": 822, "y": 430}, {"x": 807, "y": 430}]}, "text": "-"}, {"boundingBox": {"vertices": [{"x": 824, "y": 401}, {"x": 840, "y": 401}, {"x": 840, "y": 431}, {"x": 824, "y": 431}]}, "text": "1"}, {"boundingBox": {"vertices": [{"x": 843, "y": 401}, {"x": 859, "y": 401}, {"x": 859, "y": 431}, {"x": 843, "y": 431}]}, "text": "3"}, {"boundingBox": {"vertices": [{"x": 861, "y": 401}, {"x": 877, "y": 401}, {"x": 877, "y": 431}, {"x": 861, "y": 431}]}, "text": "5"}, {"boundingBox": {"vertices": [{"x": 879, "y": 402}, {"x": 896, "y": 402}, {"x": 896, "y": 432}, {"x": 879, "y": 432}]}, "text": "0"}, {"property": {"detectedBreak": {"type": "SPACE"}}, "boundingBox": {"vertices": [{"x": 899, "y": 402}, {"x": 916, "y": 402}, {"x": 916, "y": 432}, {"x": 899, "y": 432}]}, "text": "0"}]}, {"boundingBox": {"vertices": [{"x": 924, "y": 402}, {"x": 935, "y": 402}, {"x": 935, "y": 432}, {"x": 924, "y": 432}]}, "symbols": [{"boundingBox": {"vertices": [{"x": 924, "y": 402}, {"x": 935, "y": 402}, {"x": 935, "y": 432}, {"x": 924, "y": 432}]}, "text": "("}]}, {"boundingBox": {"vertices": [{"x": 937, "y": 402}, {"x": 1050, "y": 404}, {"x": 1050, "y": 435}, {"x": 937, "y": 433}]}, "symbols": [{"boundingBox": {"vertices": [{"x": 937, "y": 402}, {"x": 957, "y": 402}, {"x": 957, "y": 432}, {"x": 937, "y": 432}]}, "text": "T"}, {"boundingBox": {"vertices": [{"x": 957, "y": 403}, {"x": 973, "y": 403}, {"x": 973, "y": 433}, {"x": 957, "y": 433}]}, "text": "r"}, {"boundingBox": {"vertices": [{"x": 976, "y": 403}, {"x": 992, "y": 403}, {"x": 992, "y": 433}, {"x": 976, "y": 433}]}, "text": "a"}, {"boundingBox": {"vertices": [{"x": 994, "y": 403}, {"x": 1011, "y": 403}, {"x": 1011, "y": 433}, {"x": 994, "y": 433}]}, "text": "n"}, {"boundingBox": {"vertices": [{"x": 1013, "y": 403}, {"x": 1030, "y": 403}, {"x": 1030, "y": 433}, {"x": 1013, "y": 433}]}, "text": "s"}, {"boundingBox": {"vertices": [{"x": 1032, "y": 404}, {"x": 1050, "y": 404}, {"x": 1050, "y": 434}, {"x": 1032, "y": 434}]}, "text": "p"}]}, {"boundingBox": {"vertices": [{"x": 1052, "y": 404}, {"x": 1065, "y": 404}, {"x": 1065, "y": 434}, {"x": 1052, "y": 434}]}, "symbols": [{"property": {"detectedBreak": {"type": "EOL_SURE_SPACE"}}, "boundingBox": {"vertices": [{"x": 1052, "y": 404}, {"x": 1065, "y": 404}, {"x": 1065, "y": 434}, {"x": 1052, "y": 434}]}, "text": ")"}]}, {"boundingBox": {"vertices": [{"x": 11, "y": 430}, {"x": 181, "y": 431}, {"x": 181, "y": 457}, {"x": 11, "y": 456}]}, "symbols": [{"boundingBox": {"vertices": [{"x": 11, "y": 431}, {"x": 27, "y": 431}, {"x": 27, "y": 456}, {"x": 11, "y": 456}]}, "text": "3"}, {"boundingBox": {"vertices": [{"x": 31, "y": 431}, {"x": 49, "y": 431}, {"x": 49, "y": 456}, {"x": 31, "y": 456}]}, "text": "0"}, {"boundingBox": {"vertices": [{"x": 54, "y": 431}, {"x": 63, "y": 431}, {"x": 63, "y": 456}, {"x": 54, "y": 456}]}, "text": "."}, {"boundingBox": {"vertices": [{"x": 68, "y": 431}, {"x": 85, "y": 431}, {"x": 85, "y": 456}, {"x": 68, "y": 456}]}, "text": "9"}, {"boundingBox": {"vertices": [{"x": 92, "y": 431}, {"x": 101, "y": 431}, {"x": 101, "y": 456}, {"x": 92, "y": 456}]}, "text": "."}, {"boundingBox": {"vertices": [{"x": 108, "y": 431}, {"x": 124, "y": 431}, {"x": 124, "y": 456}, {"x": 108, "y": 456}]}, "text": "1"}, {"boundingBox": {"vertices": [{"x": 126, "y": 431}, {"x": 141, "y": 431}, {"x": 141, "y": 456}, {"x": 126, "y": 456}]}, "text": "9"}, {"boundingBox": {"vertices": [{"x": 144, "y": 431}, {"x": 162, "y": 431}, {"x": 162, "y": 456}, {"x": 144, "y": 456}]}, "text": "4"}, {"property": {"detectedBreak": {"type": "SPACE"}}, "boundingBox": {"vertices": [{"x": 163, "y": 432}, {"x": 181, "y": 432}, {"x": 181, "y": 457}, {"x": 163, "y": 457}]}, "text": "4"}]}, {"boundingBox": {"vertices": [{"x": 258, "y": 431}, {"x": 276, "y": 431}, {"x": 276, "y": 460}, {"x": 258, "y": 460}]}, "symbols": [{"boundingBox": {"vertices": [{"x": 258, "y": 431}, {"x": 276, "y": 431}, {"x": 276, "y": 460}, {"x": 258, "y": 460}]}, "text": "i"}]}, {"boundingBox": {"vertices": [{"x": 282, "y": 431}, {"x": 291, "y": 431}, {"x": 291, "y": 460}, {"x": 282, "y": 460}]}, "symbols": [{"property": {"detectedBreak": {"type": "SPACE"}}, "boundingBox": {"vertices": [{"x": 282, "y": 431}, {"x": 291, "y": 431}, {"x": 291, "y": 460}, {"x": 282, "y": 460}]}, "text": "."}]}, {"boundingBox": {"vertices": [{"x": 314, "y": 431}, {"x": 353, "y": 432}, {"x": 353, "y": 462}, {"x": 314, "y": 461}]}, "symbols": [{"boundingBox": {"vertices": [{"x": 314, "y": 431}, {"x": 332, "y": 431}, {"x": 332, "y": 460}, {"x": 314, "y": 460}]}, "text": "K"}, {"property": {"detectedBreak": {"type": "SPACE"}}, "boundingBox": {"vertices": [{"x": 336, "y": 432}, {"x": 353, "y": 432}, {"x": 353, "y": 461}, {"x": 336, "y": 461}]}, "text": "L"}]}, {"boundingBox": {"vertices": [{"x": 372, "y": 432}, {"x": 558, "y": 434}, {"x": 558, "y": 463}, {"x": 372, "y": 461}]}, "symbols": [{"boundingBox": {"vertices": [{"x": 372, "y": 432}, {"x": 389, "y": 432}, {"x": 389, "y": 461}, {"x": 372, "y": 461}]}, "text": "G"}, {"boundingBox": {"vertices": [{"x": 391, "y": 432}, {"x": 408, "y": 432}, {"x": 408, "y": 461}, {"x": 391, "y": 461}]}, "text": "o"}, {"boundingBox": {"vertices": [{"x": 410, "y": 432}, {"x": 429, "y": 432}, {"x": 429, "y": 461}, {"x": 410, "y": 461}]}, "text": "l"}, {"boundingBox": {"vertices": [{"x": 429, "y": 433}, {"x": 445, "y": 433}, {"x": 445, "y": 462}, {"x": 429, "y": 462}]}, "text": "l"}, {"boundingBox": {"vertices": [{"x": 447, "y": 433}, {"x": 464, "y": 433}, {"x": 464, "y": 462}, {"x": 447, "y": 462}]}, "text": "e"}, {"boundingBox": {"vertices": [{"x": 466, "y": 433}, {"x": 482, "y": 433}, {"x": 482, "y": 462}, {"x": 466, "y": 462}]}, "text": "s"}, {"boundingBox": {"vertices": [{"x": 486, "y": 433}, {"x": 501, "y": 433}, {"x": 501, "y": 462}, {"x": 486, "y": 462}]}, "text": "c"}, {"boundingBox": {"vertices": [{"x": 503, "y": 434}, {"x": 519, "y": 434}, {"x": 519, "y": 463}, {"x": 503, "y": 463}]}, "text": "h"}, {"boundingBox": {"vertices": [{"x": 523, "y": 434}, {"x": 538, "y": 434}, {"x": 538, "y": 463}, {"x": 523, "y": 463}]}, "text": "a"}, {"property": {"detectedBreak": {"type": "SPACE"}}, "boundingBox": {"vertices": [{"x": 543, "y": 434}, {"x": 558, "y": 434}, {"x": 558, "y": 463}, {"x": 543, "y": 463}]}, "text": "u"}]}, {"boundingBox": {"vertices": [{"x": 565, "y": 435}, {"x": 574, "y": 435}, {"x": 574, "y": 464}, {"x": 565, "y": 464}]}, "symbols": [{"boundingBox": {"vertices": [{"x": 565, "y": 435}, {"x": 574, "y": 435}, {"x": 574, "y": 464}, {"x": 565, "y": 464}]}, "text": "("}]}, {"boundingBox": {"vertices": [{"x": 577, "y": 434}, {"x": 633, "y": 435}, {"x": 633, "y": 465}, {"x": 577, "y": 464}]}, "symbols": [{"boundingBox": {"vertices": [{"x": 577, "y": 435}, {"x": 596, "y": 435}, {"x": 596, "y": 464}, {"x": 577, "y": 464}]}, "text": "K"}, {"boundingBox": {"vertices": [{"x": 598, "y": 435}, {"x": 614, "y": 435}, {"x": 614, "y": 464}, {"x": 598, "y": 464}]}, "text": "o"}, {"boundingBox": {"vertices": [{"x": 616, "y": 435}, {"x": 633, "y": 435}, {"x": 633, "y": 464}, {"x": 616, "y": 464}]}, "text": "m"}]}, {"boundingBox": {"vertices": [{"x": 640, "y": 435}, {"x": 649, "y": 435}, {"x": 649, "y": 464}, {"x": 640, "y": 464}]}, "symbols": [{"property": {"detectedBreak": {"type": "SPACE"}}, "boundingBox": {"vertices": [{"x": 640, "y": 435}, {"x": 649, "y": 435}, {"x": 649, "y": 464}, {"x": 640, "y": 464}]}, "text": "."}]}, {"boundingBox": {"vertices": [{"x": 651, "y": 435}, {"x": 821, "y": 437}, {"x": 821, "y": 467}, {"x": 651, "y": 465}]}, "symbols": [{"boundingBox": {"vertices": [{"x": 651, "y": 436}, {"x": 670, "y": 436}, {"x": 670, "y": 465}, {"x": 651, "y": 465}]}, "text": "A"}, {"boundingBox": {"vertices": [{"x": 673, "y": 436}, {"x": 690, "y": 436}, {"x": 690, "y": 465}, {"x": 673, "y": 465}]}, "text": "u"}, {"boundingBox": {"vertices": [{"x": 694, "y": 436}, {"x": 708, "y": 436}, {"x": 708, "y": 465}, {"x": 694, "y": 465}]}, "text": "s"}, {"boundingBox": {"vertices": [{"x": 712, "y": 436}, {"x": 727, "y": 436}, {"x": 727, "y": 465}, {"x": 712, "y": 465}]}, "text": "c"}, {"boundingBox": {"vertices": [{"x": 729, "y": 437}, {"x": 744, "y": 437}, {"x": 744, "y": 466}, {"x": 729, "y": 466}]}, "text": "h"}, {"boundingBox": {"vertices": [{"x": 748, "y": 437}, {"x": 765, "y": 437}, {"x": 765, "y": 466}, {"x": 748, "y": 466}]}, "text": "w"}, {"boundingBox": {"vertices": [{"x": 768, "y": 437}, {"x": 783, "y": 437}, {"x": 783, "y": 466}, {"x": 768, "y": 466}]}, "text": "i"}, {"boundingBox": {"vertices": [{"x": 786, "y": 437}, {"x": 802, "y": 437}, {"x": 802, "y": 466}, {"x": 786, "y": 466}]}, "text": "t"}, {"boundingBox": {"vertices": [{"x": 806, "y": 438}, {"x": 821, "y": 438}, {"x": 821, "y": 467}, {"x": 806, "y": 467}]}, "text": "z"}]}, {"boundingBox": {"vertices": [{"x": 827, "y": 438}, {"x": 836, "y": 438}, {"x": 836, "y": 467}, {"x": 827, "y": 467}]}, "symbols": [{"property": {"detectedBreak": {"type": "SPACE"}}, "boundingBox": {"vertices": [{"x": 827, "y": 438}, {"x": 836, "y": 438}, {"x": 836, "y": 467}, {"x": 827, "y": 467}]}, "text": ")"}]}, {"boundingBox": {"vertices": [{"x": 843, "y": 438}, {"x": 932, "y": 439}, {"x": 932, "y": 469}, {"x": 843, "y": 468}]}, "symbols": [{"boundingBox": {"vertices": [{"x": 843, "y": 438}, {"x": 857, "y": 438}, {"x": 857, "y": 467}, {"x": 843, "y": 467}]}, "text": "H"}, {"boundingBox": {"vertices": [{"x": 866, "y": 438}, {"x": 873, "y": 438}, {"x": 873, "y": 467}, {"x": 866, "y": 467}]}, "text": "."}, {"boundingBox": {"vertices": [{"x": 881, "y": 439}, {"x": 894, "y": 439}, {"x": 894, "y": 468}, {"x": 881, "y": 468}]}, "text": "N"}, {"boundingBox": {"vertices": [{"x": 900, "y": 439}, {"x": 915, "y": 439}, {"x": 915, "y": 468}, {"x": 900, "y": 468}]}, "text": "r"}, {"property": {"detectedBreak": {"type": "SPACE"}}, "boundingBox": {"vertices": [{"x": 923, "y": 439}, {"x": 932, "y": 439}, {"x": 932, "y": 468}, {"x": 923, "y": 468}]}, "text": "."}]}, {"boundingBox": {"vertices": [{"x": 937, "y": 439}, {"x": 955, "y": 439}, {"x": 955, "y": 468}, {"x": 937, "y": 468}]}, "symbols": [{"boundingBox": {"vertices": [{"x": 937, "y": 439}, {"x": 955, "y": 439}, {"x": 955, "y": 468}, {"x": 937, "y": 468}]}, "text": "B"}]}, {"boundingBox": {"vertices": [{"x": 957, "y": 440}, {"x": 973, "y": 440}, {"x": 973, "y": 469}, {"x": 957, "y": 469}]}, "symbols": [{"boundingBox": {"vertices": [{"x": 957, "y": 440}, {"x": 973, "y": 440}, {"x": 973, "y": 469}, {"x": 957, "y": 469}]}, "text": "-"}]}, {"boundingBox": {"vertices": [{"x": 975, "y": 440}, {"x": 1067, "y": 441}, {"x": 1067, "y": 470}, {"x": 975, "y": 469}]}, "symbols": [{"boundingBox": {"vertices": [{"x": 975, "y": 440}, {"x": 992, "y": 440}, {"x": 992, "y": 469}, {"x": 975, "y": 469}]}, "text": "1"}, {"boundingBox": {"vertices": [{"x": 994, "y": 440}, {"x": 1010, "y": 440}, {"x": 1010, "y": 469}, {"x": 994, "y": 469}]}, "text": "1"}, {"boundingBox": {"vertices": [{"x": 1012, "y": 440}, {"x": 1028, "y": 440}, {"x": 1028, "y": 469}, {"x": 1012, "y": 469}]}, "text": "3"}, {"boundingBox": {"vertices": [{"x": 1031, "y": 441}, {"x": 1048, "y": 441}, {"x": 1048, "y": 470}, {"x": 1031, "y": 470}]}, "text": "2"}, {"property": {"detectedBreak": {"type": "EOL_SURE_SPACE"}}, "boundingBox": {"vertices": [{"x": 1050, "y": 441}, {"x": 1067, "y": 441}, {"x": 1067, "y": 470}, {"x": 1050, "y": 470}]}, "text": "9"}]}, {"boundingBox": {"vertices": [{"x": 11, "y": 469}, {"x": 160, "y": 468}, {"x": 160, "y": 494}, {"x": 11, "y": 495}]}, "symbols": [{"boundingBox": {"vertices": [{"x": 11, "y": 470}, {"x": 29, "y": 470}, {"x": 29, "y": 495}, {"x": 11, "y": 495}]}, "text": "6"}, {"boundingBox": {"vertices": [{"x": 33, "y": 469}, {"x": 43, "y": 469}, {"x": 43, "y": 494}, {"x": 33, "y": 494}]}, "text": "."}, {"boundingBox": {"vertices": [{"x": 47, "y": 469}, {"x": 66, "y": 469}, {"x": 66, "y": 494}, {"x": 47, "y": 494}]}, "text": "2"}, {"boundingBox": {"vertices": [{"x": 71, "y": 469}, {"x": 81, "y": 469}, {"x": 81, "y": 494}, {"x": 71, "y": 494}]}, "text": "."}, {"boundingBox": {"vertices": [{"x": 87, "y": 469}, {"x": 104, "y": 469}, {"x": 104, "y": 494}, {"x": 87, "y": 494}]}, "text": "1"}, {"boundingBox": {"vertices": [{"x": 105, "y": 469}, {"x": 121, "y": 469}, {"x": 121, "y": 494}, {"x": 105, "y": 494}]}, "text": "9"}, {"boundingBox": {"vertices": [{"x": 123, "y": 469}, {"x": 141, "y": 469}, {"x": 141, "y": 494}, {"x": 123, "y": 494}]}, "text": "4"}, {"property": {"detectedBreak": {"type": "SPACE"}}, "boundingBox": {"vertices": [{"x": 144, "y": 469}, {"x": 160, "y": 469}, {"x": 160, "y": 494}, {"x": 144, "y": 494}]}, "text": "5"}]}, {"boundingBox": {"vertices": [{"x": 258, "y": 471}, {"x": 277, "y": 471}, {"x": 277, "y": 504}, {"x": 258, "y": 504}]}, "symbols": [{"boundingBox": {"vertices": [{"x": 258, "y": 471}, {"x": 277, "y": 471}, {"x": 277, "y": 504}, {"x": 258, "y": 504}]}, "text": "i"}]}, {"boundingBox": {"vertices": [{"x": 281, "y": 471}, {"x": 291, "y": 471}, {"x": 291, "y": 504}, {"x": 281, "y": 504}]}, "symbols": [{"property": {"detectedBreak": {"type": "SPACE"}}, "boundingBox": {"vertices": [{"x": 281, "y": 471}, {"x": 291, "y": 471}, {"x": 291, "y": 504}, {"x": 281, "y": 504}]}, "text": "."}]}, {"boundingBox": {"vertices": [{"x": 315, "y": 471}, {"x": 354, "y": 471}, {"x": 354, "y": 504}, {"x": 315, "y": 504}]}, "symbols": [{"boundingBox": {"vertices": [{"x": 315, "y": 471}, {"x": 333, "y": 471}, {"x": 333, "y": 504}, {"x": 315, "y": 504}]}, "text": "K"}, {"property": {"detectedBreak": {"type": "SPACE"}}, "boundingBox": {"vertices": [{"x": 335, "y": 471}, {"x": 354, "y": 471}, {"x": 354, "y": 504}, {"x": 335, "y": 504}]}, "text": "L"}]}, {"boundingBox": {"vertices": [{"x": 370, "y": 471}, {"x": 578, "y": 472}, {"x": 578, "y": 506}, {"x": 370, "y": 505}]}, "symbols": [{"boundingBox": {"vertices": [{"x": 370, "y": 471}, {"x": 388, "y": 471}, {"x": 388, "y": 504}, {"x": 370, "y": 504}]}, "text": "F"}, {"boundingBox": {"vertices": [{"x": 391, "y": 471}, {"x": 410, "y": 471}, {"x": 410, "y": 504}, {"x": 391, "y": 504}]}, "text": "l"}, {"boundingBox": {"vertices": [{"x": 409, "y": 471}, {"x": 425, "y": 471}, {"x": 425, "y": 504}, {"x": 409, "y": 504}]}, "text": "o"}, {"boundingBox": {"vertices": [{"x": 428, "y": 471}, {"x": 443, "y": 471}, {"x": 443, "y": 504}, {"x": 428, "y": 504}]}, "text": "s"}, {"boundingBox": {"vertices": [{"x": 447, "y": 471}, {"x": 462, "y": 471}, {"x": 462, "y": 504}, {"x": 447, "y": 504}]}, "text": "s"}, {"boundingBox": {"vertices": [{"x": 466, "y": 472}, {"x": 482, "y": 472}, {"x": 482, "y": 505}, {"x": 466, "y": 505}]}, "text": "e"}, {"boundingBox": {"vertices": [{"x": 484, "y": 472}, {"x": 499, "y": 472}, {"x": 499, "y": 505}, {"x": 484, "y": 505}]}, "text": "n"}, {"boundingBox": {"vertices": [{"x": 503, "y": 472}, {"x": 519, "y": 472}, {"x": 519, "y": 505}, {"x": 503, "y": 505}]}, "text": "b"}, {"boundingBox": {"vertices": [{"x": 522, "y": 472}, {"x": 538, "y": 472}, {"x": 538, "y": 505}, {"x": 522, "y": 505}]}, "text": "ü"}, {"boundingBox": {"vertices": [{"x": 540, "y": 472}, {"x": 558, "y": 472}, {"x": 558, "y": 505}, {"x": 540, "y": 505}]}, "text": "r"}, {"property": {"detectedBreak": {"type": "SPACE"}}, "boundingBox": {"vertices": [{"x": 560, "y": 472}, {"x": 578, "y": 472}, {"x": 578, "y": 505}, {"x": 560, "y": 505}]}, "text": "g"}]}, {"boundingBox": {"vertices": [{"x": 597, "y": 472}, {"x": 786, "y": 473}, {"x": 786, "y": 507}, {"x": 597, "y": 506}]}, "symbols": [{"boundingBox": {"vertices": [{"x": 597, "y": 472}, {"x": 612, "y": 472}, {"x": 612, "y": 505}, {"x": 597, "y": 505}]}, "text": "H"}, {"boundingBox": {"vertices": [{"x": 620, "y": 472}, {"x": 627, "y": 472}, {"x": 627, "y": 505}, {"x": 620, "y": 505}]}, "text": "."}, {"boundingBox": {"vertices": [{"x": 635, "y": 472}, {"x": 650, "y": 472}, {"x": 650, "y": 505}, {"x": 635, "y": 505}]}, "text": "N"}, {"boundingBox": {"vertices": [{"x": 654, "y": 472}, {"x": 671, "y": 472}, {"x": 671, "y": 505}, {"x": 654, "y": 505}]}, "text": "r"}, {"boundingBox": {"vertices": [{"x": 678, "y": 473}, {"x": 686, "y": 473}, {"x": 686, "y": 506}, {"x": 678, "y": 506}]}, "text": "."}, {"boundingBox": {"vertices": [{"x": 691, "y": 473}, {"x": 709, "y": 473}, {"x": 709, "y": 506}, {"x": 691, "y": 506}]}, "text": "4"}, {"boundingBox": {"vertices": [{"x": 711, "y": 473}, {"x": 726, "y": 473}, {"x": 726, "y": 506}, {"x": 711, "y": 506}]}, "text": "7"}, {"boundingBox": {"vertices": [{"x": 728, "y": 473}, {"x": 747, "y": 473}, {"x": 747, "y": 506}, {"x": 728, "y": 506}]}, "text": "0"}, {"boundingBox": {"vertices": [{"x": 748, "y": 473}, {"x": 768, "y": 473}, {"x": 768, "y": 506}, {"x": 748, "y": 506}]}, "text": "0"}, {"property": {"detectedBreak": {"type": "LINE_BREAK"}}, "boundingBox": {"vertices": [{"x": 766, "y": 473}, {"x": 786, "y": 473}, {"x": 786, "y": 506}, {"x": 766, "y": 506}]}, "text": "4"}]}]}, {"boundingBox": {"vertices": [{"x": 12, "y": 505}, {"x": 818, "y": 511}, {"x": 818, "y": 544}, {"x": 12, "y": 538}]}, "words": [{"boundingBox": {"vertices": [{"x": 12, "y": 508}, {"x": 181, "y": 508}, {"x": 181, "y": 533}, {"x": 12, "y": 533}]}, "symbols": [{"boundingBox": {"vertices": [{"x": 12, "y": 508}, {"x": 28, "y": 508}, {"x": 28, "y": 533}, {"x": 12, "y": 533}]}, "text": "1"}, {"boundingBox": {"vertices": [{"x": 30, "y": 508}, {"x": 49, "y": 508}, {"x": 49, "y": 533}, {"x": 30, "y": 533}]}, "text": "6"}, {"boundingBox": {"vertices": [{"x": 52, "y": 508}, {"x": 62, "y": 508}, {"x": 62, "y": 533}, {"x": 52, "y": 533}]}, "text": "."}, {"boundingBox": {"vertices": [{"x": 67, "y": 508}, {"x": 85, "y": 508}, {"x": 85, "y": 533}, {"x": 67, "y": 533}]}, "text": "3"}, {"boundingBox": {"vertices": [{"x": 90, "y": 508}, {"x": 101, "y": 508}, {"x": 101, "y": 533}, {"x": 90, "y": 533}]}, "text": "."}, {"boundingBox": {"vertices": [{"x": 107, "y": 508}, {"x": 123, "y": 508}, {"x": 123, "y": 533}, {"x": 107, "y": 533}]}, "text": "1"}, {"boundingBox": {"vertices": [{"x": 124, "y": 508}, {"x": 140, "y": 508}, {"x": 140, "y": 533}, {"x": 124, "y": 533}]}, "text": "9"}, {"boundingBox": {"vertices": [{"x": 143, "y": 508}, {"x": 161, "y": 508}, {"x": 161, "y": 533}, {"x": 143, "y": 533}]}, "text": "4"}, {"property": {"detectedBreak": {"type": "SPACE"}}, "boundingBox": {"vertices": [{"x": 163, "y": 508}, {"x": 181, "y": 508}, {"x": 181, "y": 533}, {"x": 163, "y": 533}]}, "text": "5"}]}, {"boundingBox": {"vertices": [{"x": 258, "y": 508}, {"x": 276, "y": 508}, {"x": 276, "y": 539}, {"x": 258, "y": 539}]}, "symbols": [{"boundingBox": {"vertices": [{"x": 258, "y": 508}, {"x": 276, "y": 508}, {"x": 276, "y": 539}, {"x": 258, "y": 539}]}, "text": "i"}]}, {"boundingBox": {"vertices": [{"x": 282, "y": 508}, {"x": 292, "y": 508}, {"x": 292, "y": 539}, {"x": 282, "y": 539}]}, "symbols": [{"property": {"detectedBreak": {"type": "SPACE"}}, "boundingBox": {"vertices": [{"x": 282, "y": 508}, {"x": 292, "y": 508}, {"x": 292, "y": 539}, {"x": 282, "y": 539}]}, "text": "."}]}, {"boundingBox": {"vertices": [{"x": 315, "y": 508}, {"x": 352, "y": 508}, {"x": 352, "y": 539}, {"x": 315, "y": 539}]}, "symbols": [{"boundingBox": {"vertices": [{"x": 315, "y": 508}, {"x": 332, "y": 508}, {"x": 332, "y": 539}, {"x": 315, "y": 539}]}, "text": "K"}, {"property": {"detectedBreak": {"type": "SPACE"}}, "boundingBox": {"vertices": [{"x": 335, "y": 508}, {"x": 352, "y": 508}, {"x": 352, "y": 539}, {"x": 335, "y": 539}]}, "text": "L"}]}, {"boundingBox": {"vertices": [{"x": 371, "y": 508}, {"x": 519, "y": 509}, {"x": 519, "y": 541}, {"x": 371, "y": 540}]}, "symbols": [{"boundingBox": {"vertices": [{"x": 371, "y": 508}, {"x": 389, "y": 508}, {"x": 389, "y": 539}, {"x": 371, "y": 539}]}, "text": "L"}, {"boundingBox": {"vertices": [{"x": 391, "y": 509}, {"x": 407, "y": 509}, {"x": 407, "y": 540}, {"x": 391, "y": 540}]}, "text": "e"}, {"boundingBox": {"vertices": [{"x": 408, "y": 509}, {"x": 424, "y": 509}, {"x": 424, "y": 540}, {"x": 408, "y": 540}]}, "text": "o"}, {"boundingBox": {"vertices": [{"x": 429, "y": 509}, {"x": 444, "y": 509}, {"x": 444, "y": 540}, {"x": 429, "y": 540}]}, "text": "n"}, {"boundingBox": {"vertices": [{"x": 447, "y": 509}, {"x": 463, "y": 509}, {"x": 463, "y": 540}, {"x": 447, "y": 540}]}, "text": "b"}, {"boundingBox": {"vertices": [{"x": 465, "y": 509}, {"x": 482, "y": 509}, {"x": 482, "y": 540}, {"x": 465, "y": 540}]}, "text": "e"}, {"boundingBox": {"vertices": [{"x": 483, "y": 509}, {"x": 500, "y": 509}, {"x": 500, "y": 540}, {"x": 483, "y": 540}]}, "text": "r"}, {"property": {"detectedBreak": {"type": "SPACE"}}, "boundingBox": {"vertices": [{"x": 503, "y": 510}, {"x": 519, "y": 510}, {"x": 519, "y": 541}, {"x": 503, "y": 541}]}, "text": "g"}]}, {"boundingBox": {"vertices": [{"x": 527, "y": 510}, {"x": 537, "y": 510}, {"x": 537, "y": 541}, {"x": 527, "y": 541}]}, "symbols": [{"boundingBox": {"vertices": [{"x": 527, "y": 510}, {"x": 537, "y": 510}, {"x": 537, "y": 541}, {"x": 527, "y": 541}]}, "text": "("}]}, {"boundingBox": {"vertices": [{"x": 541, "y": 510}, {"x": 597, "y": 510}, {"x": 597, "y": 541}, {"x": 541, "y": 541}]}, "symbols": [{"boundingBox": {"vertices": [{"x": 541, "y": 510}, {"x": 559, "y": 510}, {"x": 559, "y": 541}, {"x": 541, "y": 541}]}, "text": "K"}, {"boundingBox": {"vertices": [{"x": 559, "y": 510}, {"x": 576, "y": 510}, {"x": 576, "y": 541}, {"x": 559, "y": 541}]}, "text": "o"}, {"property": {"detectedBreak": {"type": "SPACE"}}, "boundingBox": {"vertices": [{"x": 578, "y": 510}, {"x": 597, "y": 510}, {"x": 597, "y": 541}, {"x": 578, "y": 541}]}, "text": "m"}]}, {"boundingBox": {"vertices": [{"x": 615, "y": 510}, {"x": 803, "y": 512}, {"x": 803, "y": 544}, {"x": 615, "y": 542}]}, "symbols": [{"boundingBox": {"vertices": [{"x": 615, "y": 511}, {"x": 631, "y": 511}, {"x": 631, "y": 542}, {"x": 615, "y": 542}]}, "text": "N"}, {"boundingBox": {"vertices": [{"x": 636, "y": 511}, {"x": 651, "y": 511}, {"x": 651, "y": 542}, {"x": 636, "y": 542}]}, "text": "a"}, {"boundingBox": {"vertices": [{"x": 653, "y": 511}, {"x": 670, "y": 511}, {"x": 670, "y": 542}, {"x": 653, "y": 542}]}, "text": "t"}, {"boundingBox": {"vertices": [{"x": 673, "y": 511}, {"x": 689, "y": 511}, {"x": 689, "y": 542}, {"x": 673, "y": 542}]}, "text": "z"}, {"boundingBox": {"vertices": [{"x": 691, "y": 511}, {"x": 710, "y": 511}, {"x": 710, "y": 542}, {"x": 691, "y": 542}]}, "text": "w"}, {"boundingBox": {"vertices": [{"x": 711, "y": 511}, {"x": 728, "y": 511}, {"x": 728, "y": 542}, {"x": 711, "y": 542}]}, "text": "e"}, {"boundingBox": {"vertices": [{"x": 730, "y": 512}, {"x": 745, "y": 512}, {"x": 745, "y": 543}, {"x": 730, "y": 543}]}, "text": "i"}, {"boundingBox": {"vertices": [{"x": 748, "y": 512}, {"x": 764, "y": 512}, {"x": 764, "y": 543}, {"x": 748, "y": 543}]}, "text": "l"}, {"boundingBox": {"vertices": [{"x": 767, "y": 512}, {"x": 784, "y": 512}, {"x": 784, "y": 543}, {"x": 767, "y": 543}]}, "text": "e"}, {"boundingBox": {"vertices": [{"x": 785, "y": 512}, {"x": 803, "y": 512}, {"x": 803, "y": 543}, {"x": 785, "y": 543}]}, "text": "r"}]}, {"boundingBox": {"vertices": [{"x": 806, "y": 512}, {"x": 818, "y": 512}, {"x": 818, "y": 543}, {"x": 806, "y": 543}]}, "symbols": [{"property": {"detectedBreak": {"type": "LINE_BREAK"}}, "boundingBox": {"vertices": [{"x": 806, "y": 512}, {"x": 818, "y": 512}, {"x": 818, "y": 543}, {"x": 806, "y": 543}]}, "text": ")"}]}]}], "blockType": "TEXT"}, {"boundingBox": {"vertices": [{"x": 9, "y": 546}, {"x": 141, "y": 546}, {"x": 141, "y": 571}, {"x": 9, "y": 571}]}, "paragraphs": [{"boundingBox": {"vertices": [{"x": 9, "y": 546}, {"x": 141, "y": 546}, {"x": 141, "y": 571}, {"x": 9, "y": 571}]}, "words": [{"boundingBox": {"vertices": [{"x": 9, "y": 546}, {"x": 141, "y": 546}, {"x": 141, "y": 571}, {"x": 9, "y": 571}]}, "symbols": [{"boundingBox": {"vertices": [{"x": 9, "y": 546}, {"x": 26, "y": 546}, {"x": 26, "y": 571}, {"x": 9, "y": 571}]}, "text": "2"}, {"boundingBox": {"vertices": [{"x": 28, "y": 546}, {"x": 48, "y": 546}, {"x": 48, "y": 571}, {"x": 28, "y": 571}]}, "text": "8"}, {"boundingBox": {"vertices": [{"x": 53, "y": 546}, {"x": 63, "y": 546}, {"x": 63, "y": 571}, {"x": 53, "y": 571}]}, "text": "."}, {"boundingBox": {"vertices": [{"x": 66, "y": 546}, {"x": 85, "y": 546}, {"x": 85, "y": 571}, {"x": 66, "y": 571}]}, "text": "3"}, {"boundingBox": {"vertices": [{"x": 91, "y": 546}, {"x": 101, "y": 546}, {"x": 101, "y": 571}, {"x": 91, "y": 571}]}, "text": "."}, {"boundingBox": {"vertices": [{"x": 104, "y": 546}, {"x": 122, "y": 546}, {"x": 122, "y": 571}, {"x": 104, "y": 571}]}, "text": "4"}, {"property": {"detectedBreak": {"type": "LINE_BREAK"}}, "boundingBox": {"vertices": [{"x": 124, "y": 546}, {"x": 141, "y": 546}, {"x": 141, "y": 571}, {"x": 124, "y": 571}]}, "text": "5"}]}]}], "blockType": "TEXT"}, {"boundingBox": {"vertices": [{"x": 9, "y": 581}, {"x": 122, "y": 583}, {"x": 121, "y": 611}, {"x": 8, "y": 609}]}, "paragraphs": [{"boundingBox": {"vertices": [{"x": 9, "y": 581}, {"x": 122, "y": 583}, {"x": 121, "y": 611}, {"x": 8, "y": 609}]}, "words": [{"boundingBox": {"vertices": [{"x": 9, "y": 581}, {"x": 122, "y": 583}, {"x": 121, "y": 611}, {"x": 8, "y": 609}]}, "symbols": [{"boundingBox": {"vertices": [{"x": 9, "y": 582}, {"x": 27, "y": 582}, {"x": 27, "y": 609}, {"x": 9, "y": 609}]}, "text": "2"}, {"boundingBox": {"vertices": [{"x": 32, "y": 582}, {"x": 43, "y": 582}, {"x": 43, "y": 609}, {"x": 32, "y": 609}]}, "text": "."}, {"boundingBox": {"vertices": [{"x": 47, "y": 582}, {"x": 65, "y": 582}, {"x": 65, "y": 609}, {"x": 47, "y": 609}]}, "text": "5"}, {"boundingBox": {"vertices": [{"x": 72, "y": 583}, {"x": 84, "y": 583}, {"x": 84, "y": 610}, {"x": 72, "y": 610}]}, "text": "."}, {"boundingBox": {"vertices": [{"x": 85, "y": 583}, {"x": 104, "y": 583}, {"x": 104, "y": 610}, {"x": 85, "y": 610}]}, "text": "4"}, {"property": {"detectedBreak": {"type": "LINE_BREAK"}}, "boundingBox": {"vertices": [{"x": 105, "y": 583}, {"x": 122, "y": 583}, {"x": 122, "y": 610}, {"x": 105, "y": 610}]}, "text": "5"}]}]}], "blockType": "TEXT"}, {"boundingBox": {"vertices": [{"x": 10, "y": 543}, {"x": 726, "y": 549}, {"x": 725, "y": 677}, {"x": 9, "y": 671}]}, "paragraphs": [{"boundingBox": {"vertices": [{"x": 256, "y": 545}, {"x": 726, "y": 550}, {"x": 725, "y": 617}, {"x": 255, "y": 612}]}, "words": [{"boundingBox": {"vertices": [{"x": 258, "y": 547}, {"x": 275, "y": 547}, {"x": 275, "y": 576}, {"x": 258, "y": 576}]}, "symbols": [{"boundingBox": {"vertices": [{"x": 258, "y": 547}, {"x": 275, "y": 547}, {"x": 275, "y": 576}, {"x": 258, "y": 576}]}, "text": "i"}]}, {"boundingBox": {"vertices": [{"x": 281, "y": 547}, {"x": 290, "y": 547}, {"x": 290, "y": 576}, {"x": 281, "y": 576}]}, "symbols": [{"property": {"detectedBreak": {"type": "SPACE"}}, "boundingBox": {"vertices": [{"x": 281, "y": 547}, {"x": 290, "y": 547}, {"x": 290, "y": 576}, {"x": 281, "y": 576}]}, "text": "."}]}, {"boundingBox": {"vertices": [{"x": 313, "y": 547}, {"x": 352, "y": 547}, {"x": 352, "y": 576}, {"x": 313, "y": 576}]}, "symbols": [{"boundingBox": {"vertices": [{"x": 313, "y": 547}, {"x": 330, "y": 547}, {"x": 330, "y": 576}, {"x": 313, "y": 576}]}, "text": "K"}, {"property": {"detectedBreak": {"type": "SPACE"}}, "boundingBox": {"vertices": [{"x": 335, "y": 547}, {"x": 352, "y": 547}, {"x": 352, "y": 576}, {"x": 335, "y": 576}]}, "text": "L"}]}, {"boundingBox": {"vertices": [{"x": 371, "y": 547}, {"x": 481, "y": 548}, {"x": 481, "y": 578}, {"x": 371, "y": 577}]}, "symbols": [{"boundingBox": {"vertices": [{"x": 371, "y": 547}, {"x": 387, "y": 547}, {"x": 387, "y": 576}, {"x": 371, "y": 576}]}, "text": "D"}, {"boundingBox": {"vertices": [{"x": 391, "y": 547}, {"x": 406, "y": 547}, {"x": 406, "y": 576}, {"x": 391, "y": 576}]}, "text": "a"}, {"boundingBox": {"vertices": [{"x": 409, "y": 548}, {"x": 425, "y": 548}, {"x": 425, "y": 577}, {"x": 409, "y": 577}]}, "text": "c"}, {"boundingBox": {"vertices": [{"x": 426, "y": 548}, {"x": 442, "y": 548}, {"x": 442, "y": 577}, {"x": 426, "y": 577}]}, "text": "h"}, {"boundingBox": {"vertices": [{"x": 447, "y": 548}, {"x": 462, "y": 548}, {"x": 462, "y": 577}, {"x": 447, "y": 577}]}, "text": "a"}, {"property": {"detectedBreak": {"type": "SPACE"}}, "boundingBox": {"vertices": [{"x": 466, "y": 548}, {"x": 481, "y": 548}, {"x": 481, "y": 577}, {"x": 466, "y": 577}]}, "text": "u"}]}, {"boundingBox": {"vertices": [{"x": 504, "y": 548}, {"x": 590, "y": 549}, {"x": 590, "y": 579}, {"x": 504, "y": 578}]}, "symbols": [{"boundingBox": {"vertices": [{"x": 504, "y": 548}, {"x": 519, "y": 548}, {"x": 519, "y": 577}, {"x": 504, "y": 577}]}, "text": "H"}, {"boundingBox": {"vertices": [{"x": 527, "y": 548}, {"x": 535, "y": 548}, {"x": 535, "y": 577}, {"x": 527, "y": 577}]}, "text": "."}, {"boundingBox": {"vertices": [{"x": 541, "y": 548}, {"x": 556, "y": 548}, {"x": 556, "y": 577}, {"x": 541, "y": 577}]}, "text": "N"}, {"boundingBox": {"vertices": [{"x": 559, "y": 549}, {"x": 576, "y": 549}, {"x": 576, "y": 578}, {"x": 559, "y": 578}]}, "text": "r"}, {"property": {"detectedBreak": {"type": "SPACE"}}, "boundingBox": {"vertices": [{"x": 582, "y": 549}, {"x": 590, "y": 549}, {"x": 590, "y": 578}, {"x": 582, "y": 578}]}, "text": "."}]}, {"boundingBox": {"vertices": [{"x": 616, "y": 549}, {"x": 726, "y": 550}, {"x": 726, "y": 579}, {"x": 616, "y": 578}]}, "symbols": [{"boundingBox": {"vertices": [{"x": 616, "y": 549}, {"x": 632, "y": 549}, {"x": 632, "y": 578}, {"x": 616, "y": 578}]}, "text": "1"}, {"boundingBox": {"vertices": [{"x": 634, "y": 549}, {"x": 651, "y": 549}, {"x": 651, "y": 578}, {"x": 634, "y": 578}]}, "text": "4"}, {"boundingBox": {"vertices": [{"x": 653, "y": 549}, {"x": 671, "y": 549}, {"x": 671, "y": 578}, {"x": 653, "y": 578}]}, "text": "6"}, {"boundingBox": {"vertices": [{"x": 671, "y": 549}, {"x": 689, "y": 549}, {"x": 689, "y": 578}, {"x": 671, "y": 578}]}, "text": "7"}, {"boundingBox": {"vertices": [{"x": 689, "y": 550}, {"x": 707, "y": 550}, {"x": 707, "y": 579}, {"x": 689, "y": 579}]}, "text": "7"}, {"property": {"detectedBreak": {"type": "EOL_SURE_SPACE"}}, "boundingBox": {"vertices": [{"x": 708, "y": 550}, {"x": 726, "y": 550}, {"x": 726, "y": 579}, {"x": 708, "y": 579}]}, "text": "2"}]}, {"property": {"detectedLanguages": [{"languageCode": "de", "confidence": 1}]}, "boundingBox": {"vertices": [{"x": 256, "y": 585}, {"x": 274, "y": 585}, {"x": 274, "y": 611}, {"x": 256, "y": 611}]}, "symbols": [{"boundingBox": {"vertices": [{"x": 256, "y": 585}, {"x": 274, "y": 585}, {"x": 274, "y": 611}, {"x": 256, "y": 611}]}, "text": "i"}]}, {"property": {"detectedLanguages": [{"languageCode": "de", "confidence": 1}]}, "boundingBox": {"vertices": [{"x": 280, "y": 585}, {"x": 291, "y": 585}, {"x": 291, "y": 611}, {"x": 280, "y": 611}]}, "symbols": [{"property": {"detectedBreak": {"type": "SPACE"}}, "boundingBox": {"vertices": [{"x": 280, "y": 585}, {"x": 291, "y": 585}, {"x": 291, "y": 611}, {"x": 280, "y": 611}]}, "text": "."}]}, {"property": {"detectedLanguages": [{"languageCode": "de", "confidence": 1}]}, "boundingBox": {"vertices": [{"x": 313, "y": 585}, {"x": 426, "y": 586}, {"x": 426, "y": 613}, {"x": 313, "y": 612}]}, "symbols": [{"boundingBox": {"vertices": [{"x": 313, "y": 585}, {"x": 331, "y": 585}, {"x": 331, "y": 611}, {"x": 313, "y": 611}]}, "text": "D"}, {"boundingBox": {"vertices": [{"x": 333, "y": 585}, {"x": 349, "y": 585}, {"x": 349, "y": 611}, {"x": 333, "y": 611}]}, "text": "a"}, {"boundingBox": {"vertices": [{"x": 352, "y": 586}, {"x": 369, "y": 586}, {"x": 369, "y": 612}, {"x": 352, "y": 612}]}, "text": "c"}, {"boundingBox": {"vertices": [{"x": 370, "y": 586}, {"x": 388, "y": 586}, {"x": 388, "y": 612}, {"x": 370, "y": 612}]}, "text": "h"}, {"boundingBox": {"vertices": [{"x": 391, "y": 586}, {"x": 406, "y": 586}, {"x": 406, "y": 612}, {"x": 391, "y": 612}]}, "text": "a"}, {"property": {"detectedBreak": {"type": "SPACE"}}, "boundingBox": {"vertices": [{"x": 409, "y": 586}, {"x": 426, "y": 586}, {"x": 426, "y": 612}, {"x": 409, "y": 612}]}, "text": "u"}]}, {"property": {"detectedLanguages": [{"languageCode": "de", "confidence": 1}]}, "boundingBox": {"vertices": [{"x": 446, "y": 587}, {"x": 577, "y": 589}, {"x": 577, "y": 615}, {"x": 446, "y": 613}]}, "symbols": [{"boundingBox": {"vertices": [{"x": 446, "y": 587}, {"x": 463, "y": 587}, {"x": 463, "y": 613}, {"x": 446, "y": 613}]}, "text": "b"}, {"boundingBox": {"vertices": [{"x": 465, "y": 587}, {"x": 484, "y": 587}, {"x": 484, "y": 613}, {"x": 465, "y": 613}]}, "text": "e"}, {"boundingBox": {"vertices": [{"x": 482, "y": 587}, {"x": 501, "y": 587}, {"x": 501, "y": 613}, {"x": 482, "y": 613}]}, "text": "f"}, {"boundingBox": {"vertices": [{"x": 501, "y": 588}, {"x": 520, "y": 588}, {"x": 520, "y": 614}, {"x": 501, "y": 614}]}, "text": "r"}, {"boundingBox": {"vertices": [{"x": 521, "y": 588}, {"x": 539, "y": 588}, {"x": 539, "y": 614}, {"x": 521, "y": 614}]}, "text": "e"}, {"boundingBox": {"vertices": [{"x": 540, "y": 588}, {"x": 558, "y": 588}, {"x": 558, "y": 614}, {"x": 540, "y": 614}]}, "text": "i"}, {"boundingBox": {"vertices": [{"x": 558, "y": 588}, {"x": 577, "y": 588}, {"x": 577, "y": 614}, {"x": 558, "y": 614}]}, "text": "t"}]}, {"property": {"detectedLanguages": [{"languageCode": "de", "confidence": 1}]}, "boundingBox": {"vertices": [{"x": 582, "y": 589}, {"x": 593, "y": 589}, {"x": 593, "y": 615}, {"x": 582, "y": 615}]}, "symbols": [{"property": {"detectedBreak": {"type": "LINE_BREAK"}}, "boundingBox": {"vertices": [{"x": 582, "y": 589}, {"x": 593, "y": 589}, {"x": 593, "y": 615}, {"x": 582, "y": 615}]}, "text": "."}]}]}, {"boundingBox": {"vertices": [{"x": 9, "y": 639}, {"x": 520, "y": 642}, {"x": 520, "y": 674}, {"x": 9, "y": 671}]}, "words": [{"property": {"detectedLanguages": [{"languageCode": "de", "confidence": 1}]}, "boundingBox": {"vertices": [{"x": 9, "y": 640}, {"x": 105, "y": 641}, {"x": 105, "y": 672}, {"x": 9, "y": 671}]}, "symbols": [{"boundingBox": {"vertices": [{"x": 9, "y": 640}, {"x": 27, "y": 640}, {"x": 27, "y": 671}, {"x": 9, "y": 671}]}, "text": "H"}, {"boundingBox": {"vertices": [{"x": 28, "y": 640}, {"x": 46, "y": 640}, {"x": 46, "y": 671}, {"x": 28, "y": 671}]}, "text": "e"}, {"boundingBox": {"vertices": [{"x": 47, "y": 640}, {"x": 65, "y": 640}, {"x": 65, "y": 671}, {"x": 47, "y": 671}]}, "text": "n"}, {"boundingBox": {"vertices": [{"x": 66, "y": 640}, {"x": 85, "y": 640}, {"x": 85, "y": 671}, {"x": 66, "y": 671}]}, "text": "r"}, {"property": {"detectedBreak": {"type": "SPACE"}}, "boundingBox": {"vertices": [{"x": 85, "y": 640}, {"x": 105, "y": 640}, {"x": 105, "y": 671}, {"x": 85, "y": 671}]}, "text": "y"}]}, {"property": {"detectedLanguages": [{"languageCode": "de", "confidence": 1}]}, "boundingBox": {"vertices": [{"x": 123, "y": 640}, {"x": 198, "y": 640}, {"x": 198, "y": 672}, {"x": 123, "y": 672}]}, "symbols": [{"boundingBox": {"vertices": [{"x": 123, "y": 640}, {"x": 141, "y": 640}, {"x": 141, "y": 671}, {"x": 123, "y": 671}]}, "text": "M"}, {"boundingBox": {"vertices": [{"x": 144, "y": 640}, {"x": 161, "y": 640}, {"x": 161, "y": 671}, {"x": 144, "y": 671}]}, "text": "a"}, {"boundingBox": {"vertices": [{"x": 161, "y": 640}, {"x": 179, "y": 640}, {"x": 179, "y": 671}, {"x": 161, "y": 671}]}, "text": "r"}, {"property": {"detectedBreak": {"type": "SPACE"}}, "boundingBox": {"vertices": [{"x": 182, "y": 641}, {"x": 198, "y": 641}, {"x": 198, "y": 672}, {"x": 182, "y": 672}]}, "text": "c"}]}, {"property": {"detectedLanguages": [{"languageCode": "de", "confidence": 1}]}, "boundingBox": {"vertices": [{"x": 218, "y": 641}, {"x": 311, "y": 642}, {"x": 311, "y": 673}, {"x": 218, "y": 672}]}, "symbols": [{"boundingBox": {"vertices": [{"x": 218, "y": 641}, {"x": 234, "y": 641}, {"x": 234, "y": 672}, {"x": 218, "y": 672}]}, "text": "S"}, {"boundingBox": {"vertices": [{"x": 237, "y": 641}, {"x": 254, "y": 641}, {"x": 254, "y": 672}, {"x": 237, "y": 672}]}, "text": "t"}, {"boundingBox": {"vertices": [{"x": 258, "y": 641}, {"x": 275, "y": 641}, {"x": 275, "y": 672}, {"x": 258, "y": 672}]}, "text": "e"}, {"boundingBox": {"vertices": [{"x": 277, "y": 641}, {"x": 294, "y": 641}, {"x": 294, "y": 672}, {"x": 277, "y": 672}]}, "text": "r"}, {"boundingBox": {"vertices": [{"x": 296, "y": 641}, {"x": 311, "y": 641}, {"x": 311, "y": 672}, {"x": 296, "y": 672}]}, "text": "n"}]}, {"property": {"detectedLanguages": [{"languageCode": "de", "confidence": 1}]}, "boundingBox": {"vertices": [{"x": 319, "y": 641}, {"x": 327, "y": 641}, {"x": 327, "y": 672}, {"x": 319, "y": 672}]}, "symbols": [{"property": {"detectedBreak": {"type": "SPACE"}}, "boundingBox": {"vertices": [{"x": 319, "y": 641}, {"x": 327, "y": 641}, {"x": 327, "y": 672}, {"x": 319, "y": 672}]}, "text": ","}]}, {"property": {"detectedLanguages": [{"languageCode": "de", "confidence": 1}]}, "boundingBox": {"vertices": [{"x": 351, "y": 641}, {"x": 520, "y": 642}, {"x": 520, "y": 674}, {"x": 351, "y": 673}]}, "symbols": [{"boundingBox": {"vertices": [{"x": 351, "y": 642}, {"x": 367, "y": 642}, {"x": 367, "y": 673}, {"x": 351, "y": 673}]}, "text": "G"}, {"boundingBox": {"vertices": [{"x": 371, "y": 642}, {"x": 387, "y": 642}, {"x": 387, "y": 673}, {"x": 371, "y": 673}]}, "text": "e"}, {"boundingBox": {"vertices": [{"x": 389, "y": 642}, {"x": 406, "y": 642}, {"x": 406, "y": 673}, {"x": 389, "y": 673}]}, "text": "r"}, {"boundingBox": {"vertices": [{"x": 408, "y": 642}, {"x": 426, "y": 642}, {"x": 426, "y": 673}, {"x": 408, "y": 673}]}, "text": "m"}, {"boundingBox": {"vertices": [{"x": 428, "y": 642}, {"x": 444, "y": 642}, {"x": 444, "y": 673}, {"x": 428, "y": 673}]}, "text": "e"}, {"boundingBox": {"vertices": [{"x": 447, "y": 642}, {"x": 466, "y": 642}, {"x": 466, "y": 673}, {"x": 447, "y": 673}]}, "text": "r"}, {"boundingBox": {"vertices": [{"x": 465, "y": 642}, {"x": 483, "y": 642}, {"x": 483, "y": 673}, {"x": 465, "y": 673}]}, "text": "i"}, {"boundingBox": {"vertices": [{"x": 485, "y": 643}, {"x": 500, "y": 643}, {"x": 500, "y": 674}, {"x": 485, "y": 674}]}, "text": "n"}, {"property": {"detectedBreak": {"type": "LINE_BREAK"}}, "boundingBox": {"vertices": [{"x": 503, "y": 643}, {"x": 520, "y": 643}, {"x": 520, "y": 674}, {"x": 503, "y": 674}]}, "text": "g"}]}]}], "blockType": "TEXT"}, {"boundingBox": {"vertices": [{"x": 8, "y": 678}, {"x": 161, "y": 679}, {"x": 161, "y": 704}, {"x": 8, "y": 703}]}, "paragraphs": [{"boundingBox": {"vertices": [{"x": 8, "y": 678}, {"x": 161, "y": 679}, {"x": 161, "y": 704}, {"x": 8, "y": 703}]}, "words": [{"boundingBox": {"vertices": [{"x": 8, "y": 678}, {"x": 161, "y": 679}, {"x": 161, "y": 704}, {"x": 8, "y": 703}]}, "symbols": [{"boundingBox": {"vertices": [{"x": 8, "y": 679}, {"x": 25, "y": 679}, {"x": 25, "y": 703}, {"x": 8, "y": 703}]}, "text": "2"}, {"boundingBox": {"vertices": [{"x": 28, "y": 679}, {"x": 46, "y": 679}, {"x": 46, "y": 703}, {"x": 28, "y": 703}]}, "text": "1"}, {"boundingBox": {"vertices": [{"x": 51, "y": 679}, {"x": 60, "y": 679}, {"x": 60, "y": 703}, {"x": 51, "y": 703}]}, "text": "."}, {"boundingBox": {"vertices": [{"x": 68, "y": 679}, {"x": 84, "y": 679}, {"x": 84, "y": 703}, {"x": 68, "y": 703}]}, "text": "1"}, {"boundingBox": {"vertices": [{"x": 86, "y": 679}, {"x": 103, "y": 679}, {"x": 103, "y": 703}, {"x": 86, "y": 703}]}, "text": "1"}, {"boundingBox": {"vertices": [{"x": 110, "y": 679}, {"x": 119, "y": 679}, {"x": 119, "y": 703}, {"x": 110, "y": 703}]}, "text": "."}, {"boundingBox": {"vertices": [{"x": 124, "y": 679}, {"x": 139, "y": 679}, {"x": 139, "y": 703}, {"x": 124, "y": 703}]}, "text": "9"}, {"property": {"detectedBreak": {"type": "LINE_BREAK"}}, "boundingBox": {"vertices": [{"x": 143, "y": 679}, {"x": 161, "y": 679}, {"x": 161, "y": 703}, {"x": 143, "y": 703}]}, "text": "0"}]}]}], "blockType": "TEXT"}, {"boundingBox": {"vertices": [{"x": 1068, "y": 633}, {"x": 1129, "y": 634}, {"x": 1128, "y": 680}, {"x": 1067, "y": 679}]}, "paragraphs": [{"boundingBox": {"vertices": [{"x": 1068, "y": 633}, {"x": 1129, "y": 634}, {"x": 1128, "y": 680}, {"x": 1067, "y": 679}]}, "words": [{"boundingBox": {"vertices": [{"x": 1068, "y": 633}, {"x": 1129, "y": 634}, {"x": 1128, "y": 680}, {"x": 1067, "y": 679}]}, "symbols": [{"boundingBox": {"vertices": [{"x": 1068, "y": 634}, {"x": 1106, "y": 635}, {"x": 1105, "y": 680}, {"x": 1067, "y": 679}]}, "text": "3"}, {"property": {"detectedBreak": {"type": "LINE_BREAK"}}, "boundingBox": {"vertices": [{"x": 1099, "y": 634}, {"x": 1129, "y": 635}, {"x": 1128, "y": 680}, {"x": 1098, "y": 679}]}, "text": "5"}]}]}], "blockType": "TEXT"}, {"boundingBox": {"vertices": [{"x": 898, "y": 685}, {"x": 1099, "y": 688}, {"x": 1099, "y": 714}, {"x": 898, "y": 711}]}, "paragraphs": [{"boundingBox": {"vertices": [{"x": 898, "y": 685}, {"x": 1099, "y": 688}, {"x": 1099, "y": 714}, {"x": 898, "y": 711}]}, "words": [{"boundingBox": {"vertices": [{"x": 898, "y": 685}, {"x": 1085, "y": 688}, {"x": 1085, "y": 714}, {"x": 898, "y": 711}]}, "symbols": [{"boundingBox": {"vertices": [{"x": 898, "y": 686}, {"x": 915, "y": 686}, {"x": 915, "y": 711}, {"x": 898, "y": 711}]}, "text": "1"}, {"boundingBox": {"vertices": [{"x": 917, "y": 686}, {"x": 934, "y": 686}, {"x": 934, "y": 711}, {"x": 917, "y": 711}]}, "text": "4"}, {"boundingBox": {"vertices": [{"x": 941, "y": 686}, {"x": 949, "y": 686}, {"x": 949, "y": 711}, {"x": 941, "y": 711}]}, "text": "."}, {"boundingBox": {"vertices": [{"x": 955, "y": 686}, {"x": 971, "y": 686}, {"x": 971, "y": 711}, {"x": 955, "y": 711}]}, "text": "5"}, {"boundingBox": {"vertices": [{"x": 978, "y": 687}, {"x": 987, "y": 687}, {"x": 987, "y": 712}, {"x": 978, "y": 712}]}, "text": "."}, {"boundingBox": {"vertices": [{"x": 990, "y": 687}, {"x": 1006, "y": 687}, {"x": 1006, "y": 712}, {"x": 990, "y": 712}]}, "text": "9"}, {"boundingBox": {"vertices": [{"x": 1012, "y": 687}, {"x": 1028, "y": 687}, {"x": 1028, "y": 712}, {"x": 1012, "y": 712}]}, "text": "1"}, {"boundingBox": {"vertices": [{"x": 1029, "y": 687}, {"x": 1048, "y": 687}, {"x": 1048, "y": 712}, {"x": 1029, "y": 712}]}, "text": "W"}, {"boundingBox": {"vertices": [{"x": 1048, "y": 688}, {"x": 1065, "y": 688}, {"x": 1065, "y": 713}, {"x": 1048, "y": 713}]}, "text": "i"}, {"boundingBox": {"vertices": [{"x": 1067, "y": 688}, {"x": 1085, "y": 688}, {"x": 1085, "y": 713}, {"x": 1067, "y": 713}]}, "text": "l"}]}, {"boundingBox": {"vertices": [{"x": 1089, "y": 688}, {"x": 1099, "y": 688}, {"x": 1099, "y": 713}, {"x": 1089, "y": 713}]}, "symbols": [{"property": {"detectedBreak": {"type": "LINE_BREAK"}}, "boundingBox": {"vertices": [{"x": 1089, "y": 688}, {"x": 1099, "y": 688}, {"x": 1099, "y": 713}, {"x": 1089, "y": 713}]}, "text": "."}]}]}], "blockType": "TEXT"}]}], "text": "STERN Viktor Israel\n106203\nJulius u. Mathilde Elisabeth Wilhelmin RUDOLPH\n17.6.43\nResi Markhoff\n18.12.1914 Berlin\ni. Berlin verhaftet\nis.\ndeutsch\n29.6.1943 n. Theresienstadt überst.i/97-13500 (Transp)\n30.9.1944 i. KL Golleschau (Kom. Auschwitz) H.Nr. B-11329\n6.2.1945 i. KL Flossenbürg H.Nr.47004\n16.3.1945 i. KL Leonberg (Kom Natzweiler)\n28.3.45\n2.5.45\ni. KL Dachau H.Nr. 146772\ni. Dachau befreit.\nHenry Marc Stern, Germering\n21.11.90\n35\n14.5.91Wil."}}]}